// converted by version 1.3
// on Sat Apr 14 14:33:45 CEST 2018

.package be/msec/smartcard {
	.aid 0x1:0x2:0x3:0x4:0x5:0x6:0x7:0x8:0x9:0x0;
	.version 1.0;

	.imports {
		0xA0:0x0:0x0:0x0:0x62:0x1:0x1 1.3;		//javacard/framework
		0xA0:0x0:0x0:0x0:0x62:0x2:0x9 1.0;		//javacardx/apdu
		0xA0:0x0:0x0:0x0:0x62:0x1:0x2 1.3;		//javacard/security
		0xA0:0x0:0x0:0x0:0x62:0x0:0x1 1.0;		//java/lang
		0xA0:0x0:0x0:0x0:0x62:0x2:0x1 1.3;		//javacardx/crypto
	}

	.applet {
		0x1:0x2:0x3:0x4:0x5:0x6:0x7:0x8:0x9:0x0:0x0 IdentityCard;
	}

	.constantPool {
		// 0
		instanceFieldRef byte[] IdentityCard/privModulus;
		// 1
		instanceFieldRef byte[] IdentityCard/privExponent;
		// 2
		instanceFieldRef byte[] IdentityCard/pubMod_CA;
		// 3
		instanceFieldRef byte[] IdentityCard/pubExp_CA;
		// 4
		instanceFieldRef byte[] IdentityCard/pubExp_G;
		// 5
		instanceFieldRef byte[] IdentityCard/pubMod_G;
		// 6
		instanceFieldRef byte[] IdentityCard/lastValidationTime;
		// 7
		instanceFieldRef byte[] IdentityCard/certificate;
		// 8
		instanceFieldRef byte[] IdentityCard/bigdata;
		// 9
		instanceFieldRef byte[] IdentityCard/smalldata;
		// 10
		instanceFieldRef byte[] IdentityCard/verysmalldata;
		// 11
		instanceFieldRef byte[] IdentityCard/PKg;
		// 12
		instanceFieldRef byte[] IdentityCard/commonCertificate;
		// 13
		instanceFieldRef byte[] IdentityCard/privExp_ComCer;
		// 14
		instanceFieldRef byte[] IdentityCard/privMod_ComCer;
		// 15
		instanceFieldRef byte[] IdentityCard/serial;
		// 16
		instanceFieldRef byte[] IdentityCard/name;
		// 17
		instanceFieldRef short IdentityCard/offset;
		// 18
		instanceFieldRef short IdentityCard/keySizeInBytes;
		// 19
		instanceFieldRef short IdentityCard/keySizeInBits;
		// 20
		instanceFieldRef 2.8 IdentityCard/privKey;
		// 21
		instanceFieldRef boolean IdentityCard/auth;
		// 22
		instanceFieldRef 0.9 IdentityCard/pin;
		// 23
		instanceFieldRef byte[] IdentityCard/date;
		// 24
		instanceFieldRef short[] IdentityCard/BUF_IN_OFFSET;
		// 25
		instanceFieldRef 2.20 IdentityCard/symKey;
		// 26
		instanceFieldRef byte[] IdentityCard/rnd;
		// 27
		instanceFieldRef byte[] IdentityCard/challenge;
		// 28
		classRef 2.8;		// javacard/security/RSAPrivateKey
		// 29
		classRef 0.9;		// javacard/framework/OwnerPIN
		// 30
		virtualMethodRef 0.3.1()V;		// register()V
		// 31
		staticMethodRef 0.8.15(SB)[S;		// javacard/framework/JCSystem.makeTransientShortArray(SB)[S
		// 32
		staticMethodRef 0.9.0(BB)V;		// javacard/framework/OwnerPIN.<init>(BB)V
		// 33
		classRef IdentityCard;
		// 34
		staticMethodRef IdentityCard/<init>()V;
		// 35
		virtualMethodRef 0.9.2()B;		// getTriesRemaining()B
		// 36
		classRef 3.2;		// java/lang/Exception
		// 37
		virtualMethodRef 0.10.1()[B;		// getBuffer()[B
		// 38
		virtualMethodRef 0.3.3()Z;		// selectingApplet()Z
		// 39
		staticMethodRef 0.7.1(S)V;		// javacard/framework/ISOException.throwIt(S)V
		// 40
		staticMethodRef IdentityCard/validatePIN(Ljavacard/framework/APDU;)V;
			.descriptor	Ljavacard/framework/APDU;	0.10;

		// 41
		staticMethodRef IdentityCard/getSerial(Ljavacard/framework/APDU;)V;
			.descriptor	Ljavacard/framework/APDU;	0.10;

		// 42
		staticMethodRef IdentityCard/getName(Ljavacard/framework/APDU;)V;
			.descriptor	Ljavacard/framework/APDU;	0.10;

		// 43
		staticMethodRef IdentityCard/sendCertificate(Ljavacard/framework/APDU;)V;
			.descriptor	Ljavacard/framework/APDU;	0.10;

		// 44
		staticMethodRef IdentityCard/sign(Ljavacard/framework/APDU;)V;
			.descriptor	Ljavacard/framework/APDU;	0.10;

		// 45
		staticMethodRef IdentityCard/updateTime(Ljavacard/framework/APDU;)V;
			.descriptor	Ljavacard/framework/APDU;	0.10;

		// 46
		staticMethodRef IdentityCard/authenticateServiceProvider(Ljavacard/framework/APDU;)V;
			.descriptor	Ljavacard/framework/APDU;	0.10;

		// 47
		staticMethodRef IdentityCard/verifyChallenge(Ljavacard/framework/APDU;)V;
			.descriptor	Ljavacard/framework/APDU;	0.10;

		// 48
		staticMethodRef IdentityCard/authenticateCard(Ljavacard/framework/APDU;)V;
			.descriptor	Ljavacard/framework/APDU;	0.10;

		// 49
		staticMethodRef IdentityCard/receiveBigData(Ljavacard/framework/APDU;)[B;
			.descriptor	Ljavacard/framework/APDU;	0.10;

		// 50
		staticMethodRef 4.1.0(BZ)Ljavacardx/crypto/Cipher;;		// javacardx/crypto/Cipher.getInstance(BZ)Ljavacardx/crypto/Cipher;
			.descriptor	Ljavacardx/crypto/Cipher;	4.1;

		// 51
		staticMethodRef 0.3.0()V;		// javacard/framework/Applet.<init>()V
		// 52
		virtualMethodRef 4.1.3(Ljavacard/security/Key;B)V;		// init(Ljavacard/security/Key;B)V
			.descriptor	Ljavacard/security/Key;	2.0;

		// 53
		virtualMethodRef 4.1.1([BSS[BS)S;		// doFinal([BSS[BS)S
		// 54
		staticMethodRef 0.16.1([BS[BSS)S;		// javacard/framework/Util.arrayCopy([BS[BSS)S
		// 55
		staticMethodRef 2.15.0(BZ)Ljavacard/security/Signature;;		// javacard/security/Signature.getInstance(BZ)Ljavacard/security/Signature;
			.descriptor	Ljavacard/security/Signature;	2.15;

		// 56
		classRef 2.9;		// javacard/security/RSAPublicKey
		// 57
		virtualMethodRef 2.15.3(Ljavacard/security/Key;B)V;		// init(Ljavacard/security/Key;B)V
			.descriptor	Ljavacard/security/Key;	2.0;

		// 58
		virtualMethodRef 2.15.7([BSS[BSS)Z;		// verify([BSS[BSS)Z
		// 59
		staticMethodRef IdentityCard/isSmaller([B[B)Z;
		// 60
		staticMethodRef IdentityCard/getSymKey()Ljavacard/security/AESKey;;
			.descriptor	Ljavacard/security/AESKey;	2.20;

		// 61
		staticMethodRef 0.8.13(SB)[B;		// javacard/framework/JCSystem.makeTransientByteArray(SB)[B
		// 62
		virtualMethodRef 0.9.8([BSB)V;		// update([BSB)V
		// 63
		staticMethodRef IdentityCard/generateRandomBytes()[B;
		// 64
		staticMethodRef 2.13.0(BSZ)Ljavacard/security/Key;;		// javacard/security/KeyBuilder.buildKey(BSZ)Ljavacard/security/Key;
			.descriptor	Ljavacard/security/Key;	2.0;

		// 65
		staticMethodRef IdentityCard/sendChallengeToSP(Ljavacard/framework/APDU;[B)Z;
			.descriptor	Ljavacard/framework/APDU;	0.10;

		// 66
		virtualMethodRef 0.10.7()S;		// setOutgoing()S
		// 67
		virtualMethodRef 0.10.9(S)V;		// setOutgoingLength(S)V
		// 68
		classRef 0.12;		// javacard/framework/APDUException
		// 69
		virtualMethodRef 0.12.1()S;		// getReason()S
		// 70
		classRef 3.5;		// java/lang/ArrayIndexOutOfBoundsException
		// 71
		virtualMethodRef 0.10.5([BSS)V;		// sendBytesLong([BSS)V
		// 72
		virtualMethodRef 0.10.15()S;		// getIncomingLength()S
		// 73
		virtualMethodRef 0.10.6()S;		// setIncomingAndReceive()S
		// 74
		virtualMethodRef 0.10.16()S;		// getOffsetCdata()S
		// 75
		virtualMethodRef 0.10.3(S)S;		// receiveBytes(S)S
		// 76
		virtualMethodRef 0.9.1([BSB)Z;		// check([BSB)Z
		// 77
		staticMethodRef 2.14.0(B)Ljavacard/security/RandomData;;		// javacard/security/RandomData.getInstance(B)Ljavacard/security/RandomData;
			.descriptor	Ljavacard/security/RandomData;	2.14;

		// 78
		virtualMethodRef 2.14.1([BSS)V;		// generateData([BSS)V
		// 79
		classRef 2.20;		// javacard/security/AESKey
		// 80
		virtualMethodRef 0.9.4()Z;		// isValidated()Z
		// 81
		virtualMethodRef 2.15.5([BSS[BS)S;		// sign([BSS[BS)S
	}

	.class public IdentityCard 0 extends 0.3 {		// extends javacard/framework/Applet

		.fields {
			private byte[] privModulus 0;		// [B
			private byte[] privExponent 1;		// [B
			private byte[] pubMod_CA 2;		// [B
			private byte[] pubExp_CA 3;		// [B
			private byte[] pubExp_G 4;		// [B
			private byte[] pubMod_G 5;		// [B
			private byte[] lastValidationTime 6;		// [B
			private byte[] certificate 7;		// [B
			private byte[] bigdata 8;		// [B
			private byte[] smalldata 9;		// [B
			private byte[] verysmalldata 10;		// [B
			private byte[] PKg 11;		// [B
			private byte[] commonCertificate 12;		// [B
			private byte[] privExp_ComCer 13;		// [B
			private byte[] privMod_ComCer 14;		// [B
			private byte[] serial 15;		// [B
			private byte[] name 16;		// [B
			private 0.9 pin 17;		// Ljavacard/framework/OwnerPIN;
			private 2.8 privKey 18;		// Ljavacard/security/RSAPrivateKey;
			private 2.20 symKey 19;		// Ljavacard/security/AESKey;
			private short[] BUF_IN_OFFSET 20;		// [S
			private byte[] date 21;		// [B
			private byte[] rnd 22;		// [B
			private byte[] challenge 23;		// [B
			private short offset 24;		// S
			private short keySizeInBytes 25;		// S
			private short keySizeInBits 26;		// S
			private boolean auth 27;		// Z
			private static final byte IDENTITY_CARD_CLA = -128;		// B
			private static final byte VALIDATE_PIN_INS = 34;		// B
			private static final byte GET_NAME_INS = 36;		// B
			private static final byte GET_SERIAL_INS = 38;		// B
			private static final byte SIGN_RANDOM_BYTE = 39;		// B
			private static final byte GET_CERTIFICATE = 40;		// B
			private static final byte GET_BIGDATA = 41;		// B
			private static final byte UPDATE_TIME = 37;		// B
			private static final byte AUTHENTICATE_SP = 33;		// B
			private static final byte VERIFY_CHALLENGE = 41;		// B
			private static final byte AUTHENTICATE_CARD = 48;		// B
			private static final byte PIN_TRY_LIMIT = 3;		// B
			private static final byte PIN_SIZE = 4;		// B
			private static final short SW_VERIFICATION_FAILED = 25344;		// S
			private static final short SW_PIN_VERIFICATION_REQUIRED = 25345;		// S
			private static final short ERROR_OUT_OF_BOUNDS = -32767;		// S
			private static final short ERROR_UNKNOW = -30584;		// S
			private static final short MAX_APDU = 240;		// S
		}

		.publicMethodTable 6 {
			equals(Ljava/lang/Object;)Z;
			register()V;
			register([BSB)V;
			selectingApplet()Z;
			deselect()V;
			getShareableInterfaceObject(Ljavacard/framework/AID;B)Ljavacard/framework/Shareable;;
			select()Z;
			process(Ljavacard/framework/APDU;)V;
		}

		.packageMethodTable 0 {
		}

		.implementedInterfaceInfoTable { 
			.interface 1.0 { 		// javacardx/apdu/ExtendedLength
			}

		}

		.method private <init>()V {
			.stack 5;
			.locals 0;

				L0:	aload_0;
					invokespecial 51;		// javacard/framework/Applet.<init>()V
					aload_0;
					bspush 64;
					newarray 11;
					dup;
					sconst_0;
					bspush -73;
					bastore;
					dup;
					sconst_1;
					bspush -43;
					bastore;
					dup;
					sconst_2;
					bspush 96;
					bastore;
					dup;
					sconst_3;
					bspush -107;
					bastore;
					dup;
					sconst_4;
					bspush 82;
					bastore;
					dup;
					sconst_5;
					bspush 25;
					bastore;
					dup;
					bspush 6;
					bspush -66;
					bastore;
					dup;
					bspush 7;
					bspush 34;
					bastore;
					dup;
					bspush 8;
					sconst_5;
					bastore;
					dup;
					bspush 9;
					bspush -58;
					bastore;
					dup;
					bspush 10;
					bspush 75;
					bastore;
					dup;
					bspush 11;
					bspush -39;
					bastore;
					dup;
					bspush 12;
					bspush -54;
					bastore;
					dup;
					bspush 13;
					bspush 43;
					bastore;
					dup;
					bspush 14;
					bspush 25;
					bastore;
					dup;
					bspush 15;
					bspush -117;
					bastore;
					dup;
					bspush 16;
					bspush 80;
					bastore;
					dup;
					bspush 17;
					bspush -62;
					bastore;
					dup;
					bspush 18;
					bspush 51;
					bastore;
					dup;
					bspush 19;
					bspush 19;
					bastore;
					dup;
					bspush 20;
					bspush 59;
					bastore;
					dup;
					bspush 21;
					bspush -70;
					bastore;
					dup;
					bspush 22;
					bspush -100;
					bastore;
					dup;
					bspush 23;
					bspush 85;
					bastore;
					dup;
					bspush 24;
					bspush 24;
					bastore;
					dup;
					bspush 25;
					bspush -57;
					bastore;
					dup;
					bspush 26;
					bspush 108;
					bastore;
					dup;
					bspush 27;
					bspush -98;
					bastore;
					dup;
					bspush 28;
					bspush -2;
					bastore;
					dup;
					bspush 29;
					sconst_1;
					bastore;
					dup;
					bspush 30;
					bspush -80;
					bastore;
					dup;
					bspush 31;
					bspush -39;
					bastore;
					dup;
					bspush 32;
					bspush 63;
					bastore;
					dup;
					bspush 33;
					bspush 93;
					bastore;
					dup;
					bspush 34;
					bspush 112;
					bastore;
					dup;
					bspush 35;
					bspush 7;
					bastore;
					dup;
					bspush 36;
					sconst_4;
					bastore;
					dup;
					bspush 37;
					bspush 18;
					bastore;
					dup;
					bspush 38;
					bspush -11;
					bastore;
					dup;
					bspush 39;
					bspush -98;
					bastore;
					dup;
					bspush 40;
					bspush 17;
					bastore;
					dup;
					bspush 41;
					bspush 126;
					bastore;
					dup;
					bspush 42;
					bspush -54;
					bastore;
					dup;
					bspush 43;
					bspush 27;
					bastore;
					dup;
					bspush 44;
					bspush -56;
					bastore;
					dup;
					bspush 45;
					bspush 33;
					bastore;
					dup;
					bspush 46;
					bspush 77;
					bastore;
					dup;
					bspush 47;
					bspush -111;
					bastore;
					dup;
					bspush 48;
					bspush -74;
					bastore;
					dup;
					bspush 49;
					bspush -78;
					bastore;
					dup;
					bspush 50;
					bspush 88;
					bastore;
					dup;
					bspush 51;
					bspush 70;
					bastore;
					dup;
					bspush 52;
					bspush -22;
					bastore;
					dup;
					bspush 53;
					bspush -3;
					bastore;
					dup;
					bspush 54;
					bspush 15;
					bastore;
					dup;
					bspush 55;
					bspush 16;
					bastore;
					dup;
					bspush 56;
					bspush 37;
					bastore;
					dup;
					bspush 57;
					bspush -18;
					bastore;
					dup;
					bspush 58;
					bspush 92;
					bastore;
					dup;
					bspush 59;
					bspush 74;
					bastore;
					dup;
					bspush 60;
					bspush 124;
					bastore;
					dup;
					bspush 61;
					bspush -107;
					bastore;
					dup;
					bspush 62;
					bspush -116;
					bastore;
					dup;
					bspush 63;
					bspush -125;
					bastore;
					putfield_a 0;		// reference be/msec/smartcard/IdentityCard.privModulus
					aload_0;
					bspush 64;
					newarray 11;
					dup;
					sconst_0;
					bspush 24;
					bastore;
					dup;
					sconst_1;
					bspush 75;
					bastore;
					dup;
					sconst_2;
					bspush 93;
					bastore;
					dup;
					sconst_3;
					bspush -79;
					bastore;
					dup;
					sconst_4;
					bspush 62;
					bastore;
					dup;
					sconst_5;
					bspush 33;
					bastore;
					dup;
					bspush 6;
					bspush 98;
					bastore;
					dup;
					bspush 7;
					bspush -52;
					bastore;
					dup;
					bspush 8;
					bspush 50;
					bastore;
					dup;
					bspush 9;
					bspush 65;
					bastore;
					dup;
					bspush 10;
					bspush 43;
					bastore;
					dup;
					bspush 11;
					bspush -125;
					bastore;
					dup;
					bspush 12;
					sconst_3;
					bastore;
					dup;
					bspush 13;
					bspush -63;
					bastore;
					dup;
					bspush 14;
					bspush -64;
					bastore;
					dup;
					bspush 15;
					bspush 101;
					bastore;
					dup;
					bspush 16;
					bspush 117;
					bastore;
					dup;
					bspush 17;
					bspush -19;
					bastore;
					dup;
					bspush 18;
					bspush -60;
					bastore;
					dup;
					bspush 19;
					bspush 60;
					bastore;
					dup;
					bspush 20;
					bspush 53;
					bastore;
					dup;
					bspush 21;
					bspush 119;
					bastore;
					dup;
					bspush 22;
					bspush -118;
					bastore;
					dup;
					bspush 23;
					bspush -13;
					bastore;
					dup;
					bspush 24;
					bspush -128;
					bastore;
					dup;
					bspush 25;
					bspush 11;
					bastore;
					dup;
					bspush 26;
					bspush -46;
					bastore;
					dup;
					bspush 27;
					bspush -30;
					bastore;
					dup;
					bspush 28;
					bspush 12;
					bastore;
					dup;
					bspush 29;
					bspush 37;
					bastore;
					dup;
					bspush 30;
					bspush -125;
					bastore;
					dup;
					bspush 31;
					bspush 14;
					bastore;
					dup;
					bspush 32;
					bspush 104;
					bastore;
					dup;
					bspush 33;
					bspush -5;
					bastore;
					dup;
					bspush 34;
					bspush -15;
					bastore;
					dup;
					bspush 35;
					bspush -120;
					bastore;
					dup;
					bspush 36;
					bspush -113;
					bastore;
					dup;
					bspush 37;
					bspush -49;
					bastore;
					dup;
					bspush 38;
					bspush -70;
					bastore;
					dup;
					bspush 39;
					bspush -78;
					bastore;
					dup;
					bspush 40;
					bspush 114;
					bastore;
					dup;
					bspush 41;
					bspush 122;
					bastore;
					dup;
					bspush 42;
					bspush 34;
					bastore;
					dup;
					bspush 43;
					bspush 114;
					bastore;
					dup;
					bspush 44;
					bspush -99;
					bastore;
					dup;
					bspush 45;
					bspush -102;
					bastore;
					dup;
					bspush 46;
					bspush 43;
					bastore;
					dup;
					bspush 47;
					bspush -43;
					bastore;
					dup;
					bspush 48;
					bspush -102;
					bastore;
					dup;
					bspush 49;
					bspush 71;
					bastore;
					dup;
					bspush 50;
					bspush 115;
					bastore;
					dup;
					bspush 51;
					bspush 116;
					bastore;
					dup;
					bspush 52;
					bspush -105;
					bastore;
					dup;
					bspush 53;
					bspush -48;
					bastore;
					dup;
					bspush 54;
					bspush -80;
					bastore;
					dup;
					bspush 55;
					bspush 109;
					bastore;
					dup;
					bspush 56;
					bspush 117;
					bastore;
					dup;
					bspush 57;
					bspush 106;
					bastore;
					dup;
					bspush 58;
					bspush 88;
					bastore;
					dup;
					bspush 59;
					bspush 6;
					bastore;
					dup;
					bspush 60;
					bspush -69;
					bastore;
					dup;
					bspush 61;
					bspush -42;
					bastore;
					dup;
					bspush 62;
					bspush -83;
					bastore;
					dup;
					bspush 63;
					bspush 25;
					bastore;
					putfield_a 1;		// reference be/msec/smartcard/IdentityCard.privExponent
					aload_0;
					bspush 64;
					newarray 11;
					dup;
					sconst_0;
					bspush -40;
					bastore;
					dup;
					sconst_1;
					bspush -96;
					bastore;
					dup;
					sconst_2;
					bspush 115;
					bastore;
					dup;
					sconst_3;
					bspush 21;
					bastore;
					dup;
					sconst_4;
					bspush -10;
					bastore;
					dup;
					sconst_5;
					bspush -66;
					bastore;
					dup;
					bspush 6;
					bspush 80;
					bastore;
					dup;
					bspush 7;
					bspush 28;
					bastore;
					dup;
					bspush 8;
					bspush -124;
					bastore;
					dup;
					bspush 9;
					bspush 29;
					bastore;
					dup;
					bspush 10;
					bspush 98;
					bastore;
					dup;
					bspush 11;
					bspush -23;
					bastore;
					dup;
					bspush 12;
					bspush -72;
					bastore;
					dup;
					bspush 13;
					bspush 60;
					bastore;
					dup;
					bspush 14;
					bspush 89;
					bastore;
					dup;
					bspush 15;
					bspush 21;
					bastore;
					dup;
					bspush 16;
					bspush -37;
					bastore;
					dup;
					bspush 17;
					bspush -122;
					bastore;
					dup;
					bspush 18;
					bspush -14;
					bastore;
					dup;
					bspush 19;
					bspush 94;
					bastore;
					dup;
					bspush 20;
					bspush -92;
					bastore;
					dup;
					bspush 21;
					bspush 48;
					bastore;
					dup;
					bspush 22;
					bspush 98;
					bastore;
					dup;
					bspush 23;
					bspush -35;
					bastore;
					dup;
					bspush 24;
					sconst_5;
					bastore;
					dup;
					bspush 25;
					bspush -37;
					bastore;
					dup;
					bspush 26;
					bspush -50;
					bastore;
					dup;
					bspush 27;
					bspush -46;
					bastore;
					dup;
					bspush 28;
					bspush 21;
					bastore;
					dup;
					bspush 29;
					bspush -117;
					bastore;
					dup;
					bspush 30;
					bspush -48;
					bastore;
					dup;
					bspush 31;
					bspush -20;
					bastore;
					dup;
					bspush 32;
					bspush 50;
					bastore;
					dup;
					bspush 33;
					bspush -80;
					bastore;
					dup;
					bspush 34;
					bspush -41;
					bastore;
					dup;
					bspush 35;
					bspush -126;
					bastore;
					dup;
					bspush 36;
					bspush -102;
					bastore;
					dup;
					bspush 37;
					bspush 63;
					bastore;
					dup;
					bspush 38;
					bspush -2;
					bastore;
					dup;
					bspush 39;
					bspush -10;
					bastore;
					dup;
					bspush 40;
					sconst_3;
					bastore;
					dup;
					bspush 41;
					bspush -86;
					bastore;
					dup;
					bspush 42;
					bspush -54;
					bastore;
					dup;
					bspush 43;
					bspush 105;
					bastore;
					dup;
					bspush 44;
					bspush -64;
					bastore;
					dup;
					bspush 45;
					bspush 47;
					bastore;
					dup;
					bspush 46;
					bspush -23;
					bastore;
					dup;
					bspush 47;
					bspush -104;
					bastore;
					dup;
					bspush 48;
					bspush -39;
					bastore;
					dup;
					bspush 49;
					bspush 35;
					bastore;
					dup;
					bspush 50;
					bspush 107;
					bastore;
					dup;
					bspush 51;
					bspush -46;
					bastore;
					dup;
					bspush 52;
					bspush -73;
					bastore;
					dup;
					bspush 53;
					sconst_2;
					bastore;
					dup;
					bspush 54;
					bspush 120;
					bastore;
					dup;
					bspush 55;
					bspush 112;
					bastore;
					dup;
					bspush 56;
					bspush -127;
					bastore;
					dup;
					bspush 57;
					bspush -37;
					bastore;
					dup;
					bspush 58;
					bspush 117;
					bastore;
					dup;
					bspush 59;
					bspush -79;
					bastore;
					dup;
					bspush 60;
					bspush 15;
					bastore;
					dup;
					bspush 61;
					bspush 9;
					bastore;
					dup;
					bspush 62;
					bspush 48;
					bastore;
					dup;
					bspush 63;
					bspush -45;
					bastore;
					putfield_a 2;		// reference be/msec/smartcard/IdentityCard.pubMod_CA
					aload_0;
					sconst_3;
					newarray 11;
					dup;
					sconst_0;
					sconst_1;
					bastore;
					dup;
					sconst_2;
					sconst_1;
					bastore;
					putfield_a 3;		// reference be/msec/smartcard/IdentityCard.pubExp_CA
					aload_0;
					sconst_3;
					newarray 11;
					dup;
					sconst_0;
					sconst_1;
					bastore;
					dup;
					sconst_2;
					sconst_1;
					bastore;
					putfield_a 4;		// reference be/msec/smartcard/IdentityCard.pubExp_G
					aload_0;
					bspush 64;
					newarray 11;
					dup;
					sconst_0;
					bspush -74;
					bastore;
					dup;
					sconst_1;
					bspush 55;
					bastore;
					dup;
					sconst_2;
					bspush 119;
					bastore;
					dup;
					sconst_3;
					bspush 89;
					bastore;
					dup;
					sconst_4;
					bspush 101;
					bastore;
					dup;
					sconst_5;
					bspush 50;
					bastore;
					dup;
					bspush 6;
					bspush 117;
					bastore;
					dup;
					bspush 7;
					bspush 36;
					bastore;
					dup;
					bspush 8;
					bspush 87;
					bastore;
					dup;
					bspush 9;
					bspush -53;
					bastore;
					dup;
					bspush 10;
					bspush -95;
					bastore;
					dup;
					bspush 11;
					bspush 37;
					bastore;
					dup;
					bspush 12;
					bspush -98;
					bastore;
					dup;
					bspush 13;
					bspush 14;
					bastore;
					dup;
					bspush 14;
					bspush 46;
					bastore;
					dup;
					bspush 15;
					bspush 51;
					bastore;
					dup;
					bspush 16;
					bspush 74;
					bastore;
					dup;
					bspush 17;
					bspush -2;
					bastore;
					dup;
					bspush 18;
					bspush 126;
					bastore;
					dup;
					bspush 19;
					bspush -50;
					bastore;
					dup;
					bspush 20;
					bspush 29;
					bastore;
					dup;
					bspush 21;
					bspush -58;
					bastore;
					dup;
					bspush 22;
					sconst_2;
					bastore;
					dup;
					bspush 23;
					bspush -67;
					bastore;
					dup;
					bspush 24;
					bspush 13;
					bastore;
					dup;
					bspush 25;
					bspush 44;
					bastore;
					dup;
					bspush 26;
					bspush -94;
					bastore;
					dup;
					bspush 27;
					bspush -30;
					bastore;
					dup;
					bspush 28;
					bspush 63;
					bastore;
					dup;
					bspush 29;
					bspush -94;
					bastore;
					dup;
					bspush 30;
					bspush -98;
					bastore;
					dup;
					bspush 31;
					bspush 63;
					bastore;
					dup;
					bspush 32;
					bspush -95;
					bastore;
					dup;
					bspush 33;
					bspush 38;
					bastore;
					dup;
					bspush 34;
					bspush 16;
					bastore;
					dup;
					bspush 35;
					bspush -9;
					bastore;
					dup;
					bspush 36;
					bspush -68;
					bastore;
					dup;
					bspush 37;
					bspush 94;
					bastore;
					dup;
					bspush 38;
					bspush 45;
					bastore;
					dup;
					bspush 39;
					bspush -89;
					bastore;
					dup;
					bspush 40;
					bspush -43;
					bastore;
					dup;
					bspush 41;
					bspush -39;
					bastore;
					dup;
					bspush 42;
					bspush -42;
					bastore;
					dup;
					bspush 43;
					bspush -39;
					bastore;
					dup;
					bspush 44;
					bspush -52;
					bastore;
					dup;
					bspush 45;
					bspush 80;
					bastore;
					dup;
					bspush 46;
					bspush 54;
					bastore;
					dup;
					bspush 47;
					sconst_3;
					bastore;
					dup;
					bspush 48;
					bspush -88;
					bastore;
					dup;
					bspush 49;
					bspush 77;
					bastore;
					dup;
					bspush 50;
					bspush 78;
					bastore;
					dup;
					bspush 51;
					bspush -128;
					bastore;
					dup;
					bspush 52;
					bspush 99;
					bastore;
					dup;
					bspush 53;
					bspush -17;
					bastore;
					dup;
					bspush 54;
					bspush -6;
					bastore;
					dup;
					bspush 55;
					bspush 62;
					bastore;
					dup;
					bspush 56;
					bspush 40;
					bastore;
					dup;
					bspush 57;
					bspush 29;
					bastore;
					dup;
					bspush 58;
					bspush 29;
					bastore;
					dup;
					bspush 59;
					bspush 25;
					bastore;
					dup;
					bspush 60;
					bspush 27;
					bastore;
					dup;
					bspush 61;
					bspush -40;
					bastore;
					dup;
					bspush 62;
					bspush -71;
					bastore;
					dup;
					bspush 63;
					bspush -127;
					bastore;
					putfield_a 5;		// reference be/msec/smartcard/IdentityCard.pubMod_G
					aload_0;
					sconst_1;
					newarray 11;
					putfield_a 6;		// reference be/msec/smartcard/IdentityCard.lastValidationTime
					aload_0;
					sspush 449;
					newarray 11;
					dup;
					sconst_0;
					bspush 48;
					bastore;
					dup;
					sconst_1;
					bspush -126;
					bastore;
					dup;
					sconst_2;
					sconst_1;
					bastore;
					dup;
					sconst_3;
					bspush -67;
					bastore;
					dup;
					sconst_4;
					bspush 48;
					bastore;
					dup;
					sconst_5;
					bspush -126;
					bastore;
					dup;
					bspush 6;
					sconst_1;
					bastore;
					dup;
					bspush 7;
					bspush 103;
					bastore;
					dup;
					bspush 8;
					bspush -96;
					bastore;
					dup;
					bspush 9;
					sconst_3;
					bastore;
					dup;
					bspush 10;
					sconst_2;
					bastore;
					dup;
					bspush 11;
					sconst_1;
					bastore;
					dup;
					bspush 12;
					sconst_2;
					bastore;
					dup;
					bspush 13;
					sconst_2;
					bastore;
					dup;
					bspush 14;
					sconst_5;
					bastore;
					dup;
					bspush 16;
					bspush -73;
					bastore;
					dup;
					bspush 17;
					bspush -43;
					bastore;
					dup;
					bspush 18;
					bspush 96;
					bastore;
					dup;
					bspush 19;
					bspush -107;
					bastore;
					dup;
					bspush 20;
					bspush 48;
					bastore;
					dup;
					bspush 21;
					bspush 13;
					bastore;
					dup;
					bspush 22;
					bspush 6;
					bastore;
					dup;
					bspush 23;
					bspush 9;
					bastore;
					dup;
					bspush 24;
					bspush 42;
					bastore;
					dup;
					bspush 25;
					bspush -122;
					bastore;
					dup;
					bspush 26;
					bspush 72;
					bastore;
					dup;
					bspush 27;
					bspush -122;
					bastore;
					dup;
					bspush 28;
					bspush -9;
					bastore;
					dup;
					bspush 29;
					bspush 13;
					bastore;
					dup;
					bspush 30;
					sconst_1;
					bastore;
					dup;
					bspush 31;
					sconst_1;
					bastore;
					dup;
					bspush 32;
					sconst_5;
					bastore;
					dup;
					bspush 33;
					sconst_5;
					bastore;
					dup;
					bspush 35;
					bspush 48;
					bastore;
					dup;
					bspush 36;
					bspush 100;
					bastore;
					dup;
					bspush 37;
					bspush 49;
					bastore;
					dup;
					bspush 38;
					bspush 11;
					bastore;
					dup;
					bspush 39;
					bspush 48;
					bastore;
					dup;
					bspush 40;
					bspush 9;
					bastore;
					dup;
					bspush 41;
					bspush 6;
					bastore;
					dup;
					bspush 42;
					sconst_3;
					bastore;
					dup;
					bspush 43;
					bspush 85;
					bastore;
					dup;
					bspush 44;
					sconst_4;
					bastore;
					dup;
					bspush 45;
					bspush 6;
					bastore;
					dup;
					bspush 46;
					bspush 19;
					bastore;
					dup;
					bspush 47;
					sconst_2;
					bastore;
					dup;
					bspush 48;
					bspush 66;
					bastore;
					dup;
					bspush 49;
					bspush 69;
					bastore;
					dup;
					bspush 50;
					bspush 49;
					bastore;
					dup;
					bspush 51;
					bspush 13;
					bastore;
					dup;
					bspush 52;
					bspush 48;
					bastore;
					dup;
					bspush 53;
					bspush 11;
					bastore;
					dup;
					bspush 54;
					bspush 6;
					bastore;
					dup;
					bspush 55;
					sconst_3;
					bastore;
					dup;
					bspush 56;
					bspush 85;
					bastore;
					dup;
					bspush 57;
					sconst_4;
					bastore;
					dup;
					bspush 58;
					bspush 7;
					bastore;
					dup;
					bspush 59;
					bspush 12;
					bastore;
					dup;
					bspush 60;
					sconst_4;
					bastore;
					dup;
					bspush 61;
					bspush 71;
					bastore;
					dup;
					bspush 62;
					bspush 101;
					bastore;
					dup;
					bspush 63;
					bspush 110;
					bastore;
					dup;
					bspush 64;
					bspush 116;
					bastore;
					dup;
					bspush 65;
					bspush 49;
					bastore;
					dup;
					bspush 66;
					bspush 25;
					bastore;
					dup;
					bspush 67;
					bspush 48;
					bastore;
					dup;
					bspush 68;
					bspush 23;
					bastore;
					dup;
					bspush 69;
					bspush 6;
					bastore;
					dup;
					bspush 70;
					sconst_3;
					bastore;
					dup;
					bspush 71;
					bspush 85;
					bastore;
					dup;
					bspush 72;
					sconst_4;
					bastore;
					dup;
					bspush 73;
					bspush 10;
					bastore;
					dup;
					bspush 74;
					bspush 12;
					bastore;
					dup;
					bspush 75;
					bspush 16;
					bastore;
					dup;
					bspush 76;
					bspush 75;
					bastore;
					dup;
					bspush 77;
					bspush 97;
					bastore;
					dup;
					bspush 78;
					bspush 72;
					bastore;
					dup;
					bspush 79;
					bspush 111;
					bastore;
					dup;
					bspush 80;
					bspush 32;
					bastore;
					dup;
					bspush 81;
					bspush 83;
					bastore;
					dup;
					bspush 82;
					bspush 105;
					bastore;
					dup;
					bspush 83;
					bspush 110;
					bastore;
					dup;
					bspush 84;
					bspush 116;
					bastore;
					dup;
					bspush 85;
					bspush 45;
					bastore;
					dup;
					bspush 86;
					bspush 76;
					bastore;
					dup;
					bspush 87;
					bspush 105;
					bastore;
					dup;
					bspush 88;
					bspush 101;
					bastore;
					dup;
					bspush 89;
					bspush 118;
					bastore;
					dup;
					bspush 90;
					bspush 101;
					bastore;
					dup;
					bspush 91;
					bspush 110;
					bastore;
					dup;
					bspush 92;
					bspush 49;
					bastore;
					dup;
					bspush 93;
					bspush 20;
					bastore;
					dup;
					bspush 94;
					bspush 48;
					bastore;
					dup;
					bspush 95;
					bspush 18;
					bastore;
					dup;
					bspush 96;
					bspush 6;
					bastore;
					dup;
					bspush 97;
					sconst_3;
					bastore;
					dup;
					bspush 98;
					bspush 85;
					bastore;
					dup;
					bspush 99;
					sconst_4;
					bastore;
					dup;
					bspush 100;
					bspush 11;
					bastore;
					dup;
					bspush 101;
					bspush 12;
					bastore;
					dup;
					bspush 102;
					bspush 11;
					bastore;
					dup;
					bspush 103;
					bspush 86;
					bastore;
					dup;
					bspush 104;
					bspush 97;
					bastore;
					dup;
					bspush 105;
					bspush 107;
					bastore;
					dup;
					bspush 106;
					bspush 103;
					bastore;
					dup;
					bspush 107;
					bspush 114;
					bastore;
					dup;
					bspush 108;
					bspush 111;
					bastore;
					dup;
					bspush 109;
					bspush 101;
					bastore;
					dup;
					bspush 110;
					bspush 112;
					bastore;
					dup;
					bspush 111;
					bspush 32;
					bastore;
					dup;
					bspush 112;
					bspush 73;
					bastore;
					dup;
					bspush 113;
					bspush 84;
					bastore;
					dup;
					bspush 114;
					bspush 49;
					bastore;
					dup;
					bspush 115;
					bspush 21;
					bastore;
					dup;
					bspush 116;
					bspush 48;
					bastore;
					dup;
					bspush 117;
					bspush 19;
					bastore;
					dup;
					bspush 118;
					bspush 6;
					bastore;
					dup;
					bspush 119;
					sconst_3;
					bastore;
					dup;
					bspush 120;
					bspush 85;
					bastore;
					dup;
					bspush 121;
					sconst_4;
					bastore;
					dup;
					bspush 122;
					sconst_3;
					bastore;
					dup;
					bspush 123;
					bspush 12;
					bastore;
					dup;
					bspush 124;
					bspush 12;
					bastore;
					dup;
					bspush 125;
					bspush 74;
					bastore;
					dup;
					bspush 126;
					bspush 97;
					bastore;
					dup;
					bspush 127;
					bspush 110;
					bastore;
					dup;
					sspush 128;
					bspush 32;
					bastore;
					dup;
					sspush 129;
					bspush 86;
					bastore;
					dup;
					sspush 130;
					bspush 111;
					bastore;
					dup;
					sspush 131;
					bspush 115;
					bastore;
					dup;
					sspush 132;
					bspush 115;
					bastore;
					dup;
					sspush 133;
					bspush 97;
					bastore;
					dup;
					sspush 134;
					bspush 101;
					bastore;
					dup;
					sspush 135;
					bspush 114;
					bastore;
					dup;
					sspush 136;
					bspush 116;
					bastore;
					dup;
					sspush 137;
					bspush 48;
					bastore;
					dup;
					sspush 138;
					bspush 32;
					bastore;
					dup;
					sspush 139;
					bspush 23;
					bastore;
					dup;
					sspush 140;
					bspush 13;
					bastore;
					dup;
					sspush 141;
					bspush 49;
					bastore;
					dup;
					sspush 142;
					bspush 48;
					bastore;
					dup;
					sspush 143;
					bspush 48;
					bastore;
					dup;
					sspush 144;
					bspush 50;
					bastore;
					dup;
					sspush 145;
					bspush 50;
					bastore;
					dup;
					sspush 146;
					bspush 52;
					bastore;
					dup;
					sspush 147;
					bspush 48;
					bastore;
					dup;
					sspush 148;
					bspush 57;
					bastore;
					dup;
					sspush 149;
					bspush 52;
					bastore;
					dup;
					sspush 150;
					bspush 51;
					bastore;
					dup;
					sspush 151;
					bspush 48;
					bastore;
					dup;
					sspush 152;
					bspush 50;
					bastore;
					dup;
					sspush 153;
					bspush 90;
					bastore;
					dup;
					sspush 154;
					bspush 24;
					bastore;
					dup;
					sspush 155;
					bspush 15;
					bastore;
					dup;
					sspush 156;
					bspush 53;
					bastore;
					dup;
					sspush 157;
					bspush 49;
					bastore;
					dup;
					sspush 158;
					bspush 55;
					bastore;
					dup;
					sspush 159;
					bspush 57;
					bastore;
					dup;
					sspush 160;
					bspush 48;
					bastore;
					dup;
					sspush 161;
					bspush 49;
					bastore;
					dup;
					sspush 162;
					bspush 48;
					bastore;
					dup;
					sspush 163;
					bspush 57;
					bastore;
					dup;
					sspush 164;
					bspush 49;
					bastore;
					dup;
					sspush 165;
					bspush 57;
					bastore;
					dup;
					sspush 166;
					bspush 50;
					bastore;
					dup;
					sspush 167;
					bspush 57;
					bastore;
					dup;
					sspush 168;
					bspush 52;
					bastore;
					dup;
					sspush 169;
					bspush 50;
					bastore;
					dup;
					sspush 170;
					bspush 90;
					bastore;
					dup;
					sspush 171;
					bspush 48;
					bastore;
					dup;
					sspush 172;
					bspush 100;
					bastore;
					dup;
					sspush 173;
					bspush 49;
					bastore;
					dup;
					sspush 174;
					bspush 11;
					bastore;
					dup;
					sspush 175;
					bspush 48;
					bastore;
					dup;
					sspush 176;
					bspush 9;
					bastore;
					dup;
					sspush 177;
					bspush 6;
					bastore;
					dup;
					sspush 178;
					sconst_3;
					bastore;
					dup;
					sspush 179;
					bspush 85;
					bastore;
					dup;
					sspush 180;
					sconst_4;
					bastore;
					dup;
					sspush 181;
					bspush 6;
					bastore;
					dup;
					sspush 182;
					bspush 19;
					bastore;
					dup;
					sspush 183;
					sconst_2;
					bastore;
					dup;
					sspush 184;
					bspush 66;
					bastore;
					dup;
					sspush 185;
					bspush 69;
					bastore;
					dup;
					sspush 186;
					bspush 49;
					bastore;
					dup;
					sspush 187;
					bspush 13;
					bastore;
					dup;
					sspush 188;
					bspush 48;
					bastore;
					dup;
					sspush 189;
					bspush 11;
					bastore;
					dup;
					sspush 190;
					bspush 6;
					bastore;
					dup;
					sspush 191;
					sconst_3;
					bastore;
					dup;
					sspush 192;
					bspush 85;
					bastore;
					dup;
					sspush 193;
					sconst_4;
					bastore;
					dup;
					sspush 194;
					bspush 7;
					bastore;
					dup;
					sspush 195;
					bspush 12;
					bastore;
					dup;
					sspush 196;
					sconst_4;
					bastore;
					dup;
					sspush 197;
					bspush 71;
					bastore;
					dup;
					sspush 198;
					bspush 101;
					bastore;
					dup;
					sspush 199;
					bspush 110;
					bastore;
					dup;
					sspush 200;
					bspush 116;
					bastore;
					dup;
					sspush 201;
					bspush 49;
					bastore;
					dup;
					sspush 202;
					bspush 25;
					bastore;
					dup;
					sspush 203;
					bspush 48;
					bastore;
					dup;
					sspush 204;
					bspush 23;
					bastore;
					dup;
					sspush 205;
					bspush 6;
					bastore;
					dup;
					sspush 206;
					sconst_3;
					bastore;
					dup;
					sspush 207;
					bspush 85;
					bastore;
					dup;
					sspush 208;
					sconst_4;
					bastore;
					dup;
					sspush 209;
					bspush 10;
					bastore;
					dup;
					sspush 210;
					bspush 12;
					bastore;
					dup;
					sspush 211;
					bspush 16;
					bastore;
					dup;
					sspush 212;
					bspush 75;
					bastore;
					dup;
					sspush 213;
					bspush 97;
					bastore;
					dup;
					sspush 214;
					bspush 72;
					bastore;
					dup;
					sspush 215;
					bspush 111;
					bastore;
					dup;
					sspush 216;
					bspush 32;
					bastore;
					dup;
					sspush 217;
					bspush 83;
					bastore;
					dup;
					sspush 218;
					bspush 105;
					bastore;
					dup;
					sspush 219;
					bspush 110;
					bastore;
					dup;
					sspush 220;
					bspush 116;
					bastore;
					dup;
					sspush 221;
					bspush 45;
					bastore;
					dup;
					sspush 222;
					bspush 76;
					bastore;
					dup;
					sspush 223;
					bspush 105;
					bastore;
					dup;
					sspush 224;
					bspush 101;
					bastore;
					dup;
					sspush 225;
					bspush 118;
					bastore;
					dup;
					sspush 226;
					bspush 101;
					bastore;
					dup;
					sspush 227;
					bspush 110;
					bastore;
					dup;
					sspush 228;
					bspush 49;
					bastore;
					dup;
					sspush 229;
					bspush 20;
					bastore;
					dup;
					sspush 230;
					bspush 48;
					bastore;
					dup;
					sspush 231;
					bspush 18;
					bastore;
					dup;
					sspush 232;
					bspush 6;
					bastore;
					dup;
					sspush 233;
					sconst_3;
					bastore;
					dup;
					sspush 234;
					bspush 85;
					bastore;
					dup;
					sspush 235;
					sconst_4;
					bastore;
					dup;
					sspush 236;
					bspush 11;
					bastore;
					dup;
					sspush 237;
					bspush 12;
					bastore;
					dup;
					sspush 238;
					bspush 11;
					bastore;
					dup;
					sspush 239;
					bspush 86;
					bastore;
					dup;
					sspush 240;
					bspush 97;
					bastore;
					dup;
					sspush 241;
					bspush 107;
					bastore;
					dup;
					sspush 242;
					bspush 103;
					bastore;
					dup;
					sspush 243;
					bspush 114;
					bastore;
					dup;
					sspush 244;
					bspush 111;
					bastore;
					dup;
					sspush 245;
					bspush 101;
					bastore;
					dup;
					sspush 246;
					bspush 112;
					bastore;
					dup;
					sspush 247;
					bspush 32;
					bastore;
					dup;
					sspush 248;
					bspush 73;
					bastore;
					dup;
					sspush 249;
					bspush 84;
					bastore;
					dup;
					sspush 250;
					bspush 49;
					bastore;
					dup;
					sspush 251;
					bspush 21;
					bastore;
					dup;
					sspush 252;
					bspush 48;
					bastore;
					dup;
					sspush 253;
					bspush 19;
					bastore;
					dup;
					sspush 254;
					bspush 6;
					bastore;
					dup;
					sspush 255;
					sconst_3;
					bastore;
					dup;
					sspush 256;
					bspush 85;
					bastore;
					dup;
					sspush 257;
					sconst_4;
					bastore;
					dup;
					sspush 258;
					sconst_3;
					bastore;
					dup;
					sspush 259;
					bspush 12;
					bastore;
					dup;
					sspush 260;
					bspush 12;
					bastore;
					dup;
					sspush 261;
					bspush 74;
					bastore;
					dup;
					sspush 262;
					bspush 97;
					bastore;
					dup;
					sspush 263;
					bspush 110;
					bastore;
					dup;
					sspush 264;
					bspush 32;
					bastore;
					dup;
					sspush 265;
					bspush 86;
					bastore;
					dup;
					sspush 266;
					bspush 111;
					bastore;
					dup;
					sspush 267;
					bspush 115;
					bastore;
					dup;
					sspush 268;
					bspush 115;
					bastore;
					dup;
					sspush 269;
					bspush 97;
					bastore;
					dup;
					sspush 270;
					bspush 101;
					bastore;
					dup;
					sspush 271;
					bspush 114;
					bastore;
					dup;
					sspush 272;
					bspush 116;
					bastore;
					dup;
					sspush 273;
					bspush 48;
					bastore;
					dup;
					sspush 274;
					bspush 92;
					bastore;
					dup;
					sspush 275;
					bspush 48;
					bastore;
					dup;
					sspush 276;
					bspush 13;
					bastore;
					dup;
					sspush 277;
					bspush 6;
					bastore;
					dup;
					sspush 278;
					bspush 9;
					bastore;
					dup;
					sspush 279;
					bspush 42;
					bastore;
					dup;
					sspush 280;
					bspush -122;
					bastore;
					dup;
					sspush 281;
					bspush 72;
					bastore;
					dup;
					sspush 282;
					bspush -122;
					bastore;
					dup;
					sspush 283;
					bspush -9;
					bastore;
					dup;
					sspush 284;
					bspush 13;
					bastore;
					dup;
					sspush 285;
					sconst_1;
					bastore;
					dup;
					sspush 286;
					sconst_1;
					bastore;
					dup;
					sspush 287;
					sconst_1;
					bastore;
					dup;
					sspush 288;
					sconst_5;
					bastore;
					dup;
					sspush 290;
					sconst_3;
					bastore;
					dup;
					sspush 291;
					bspush 75;
					bastore;
					dup;
					sspush 293;
					bspush 48;
					bastore;
					dup;
					sspush 294;
					bspush 72;
					bastore;
					dup;
					sspush 295;
					sconst_2;
					bastore;
					dup;
					sspush 296;
					bspush 65;
					bastore;
					dup;
					sspush 298;
					bspush -73;
					bastore;
					dup;
					sspush 299;
					bspush -43;
					bastore;
					dup;
					sspush 300;
					bspush 96;
					bastore;
					dup;
					sspush 301;
					bspush -107;
					bastore;
					dup;
					sspush 302;
					bspush 82;
					bastore;
					dup;
					sspush 303;
					bspush 25;
					bastore;
					dup;
					sspush 304;
					bspush -66;
					bastore;
					dup;
					sspush 305;
					bspush 34;
					bastore;
					dup;
					sspush 306;
					sconst_5;
					bastore;
					dup;
					sspush 307;
					bspush -58;
					bastore;
					dup;
					sspush 308;
					bspush 75;
					bastore;
					dup;
					sspush 309;
					bspush -39;
					bastore;
					dup;
					sspush 310;
					bspush -54;
					bastore;
					dup;
					sspush 311;
					bspush 43;
					bastore;
					dup;
					sspush 312;
					bspush 25;
					bastore;
					dup;
					sspush 313;
					bspush -117;
					bastore;
					dup;
					sspush 314;
					bspush 80;
					bastore;
					dup;
					sspush 315;
					bspush -62;
					bastore;
					dup;
					sspush 316;
					bspush 51;
					bastore;
					dup;
					sspush 317;
					bspush 19;
					bastore;
					dup;
					sspush 318;
					bspush 59;
					bastore;
					dup;
					sspush 319;
					bspush -70;
					bastore;
					dup;
					sspush 320;
					bspush -100;
					bastore;
					dup;
					sspush 321;
					bspush 85;
					bastore;
					dup;
					sspush 322;
					bspush 24;
					bastore;
					dup;
					sspush 323;
					bspush -57;
					bastore;
					dup;
					sspush 324;
					bspush 108;
					bastore;
					dup;
					sspush 325;
					bspush -98;
					bastore;
					dup;
					sspush 326;
					bspush -2;
					bastore;
					dup;
					sspush 327;
					sconst_1;
					bastore;
					dup;
					sspush 328;
					bspush -80;
					bastore;
					dup;
					sspush 329;
					bspush -39;
					bastore;
					dup;
					sspush 330;
					bspush 63;
					bastore;
					dup;
					sspush 331;
					bspush 93;
					bastore;
					dup;
					sspush 332;
					bspush 112;
					bastore;
					dup;
					sspush 333;
					bspush 7;
					bastore;
					dup;
					sspush 334;
					sconst_4;
					bastore;
					dup;
					sspush 335;
					bspush 18;
					bastore;
					dup;
					sspush 336;
					bspush -11;
					bastore;
					dup;
					sspush 337;
					bspush -98;
					bastore;
					dup;
					sspush 338;
					bspush 17;
					bastore;
					dup;
					sspush 339;
					bspush 126;
					bastore;
					dup;
					sspush 340;
					bspush -54;
					bastore;
					dup;
					sspush 341;
					bspush 27;
					bastore;
					dup;
					sspush 342;
					bspush -56;
					bastore;
					dup;
					sspush 343;
					bspush 33;
					bastore;
					dup;
					sspush 344;
					bspush 77;
					bastore;
					dup;
					sspush 345;
					bspush -111;
					bastore;
					dup;
					sspush 346;
					bspush -74;
					bastore;
					dup;
					sspush 347;
					bspush -78;
					bastore;
					dup;
					sspush 348;
					bspush 88;
					bastore;
					dup;
					sspush 349;
					bspush 70;
					bastore;
					dup;
					sspush 350;
					bspush -22;
					bastore;
					dup;
					sspush 351;
					bspush -3;
					bastore;
					dup;
					sspush 352;
					bspush 15;
					bastore;
					dup;
					sspush 353;
					bspush 16;
					bastore;
					dup;
					sspush 354;
					bspush 37;
					bastore;
					dup;
					sspush 355;
					bspush -18;
					bastore;
					dup;
					sspush 356;
					bspush 92;
					bastore;
					dup;
					sspush 357;
					bspush 74;
					bastore;
					dup;
					sspush 358;
					bspush 124;
					bastore;
					dup;
					sspush 359;
					bspush -107;
					bastore;
					dup;
					sspush 360;
					bspush -116;
					bastore;
					dup;
					sspush 361;
					bspush -125;
					bastore;
					dup;
					sspush 362;
					sconst_2;
					bastore;
					dup;
					sspush 363;
					sconst_3;
					bastore;
					dup;
					sspush 364;
					sconst_1;
					bastore;
					dup;
					sspush 366;
					sconst_1;
					bastore;
					dup;
					sspush 367;
					bspush 48;
					bastore;
					dup;
					sspush 368;
					bspush 13;
					bastore;
					dup;
					sspush 369;
					bspush 6;
					bastore;
					dup;
					sspush 370;
					bspush 9;
					bastore;
					dup;
					sspush 371;
					bspush 42;
					bastore;
					dup;
					sspush 372;
					bspush -122;
					bastore;
					dup;
					sspush 373;
					bspush 72;
					bastore;
					dup;
					sspush 374;
					bspush -122;
					bastore;
					dup;
					sspush 375;
					bspush -9;
					bastore;
					dup;
					sspush 376;
					bspush 13;
					bastore;
					dup;
					sspush 377;
					sconst_1;
					bastore;
					dup;
					sspush 378;
					sconst_1;
					bastore;
					dup;
					sspush 379;
					sconst_5;
					bastore;
					dup;
					sspush 380;
					sconst_5;
					bastore;
					dup;
					sspush 382;
					sconst_3;
					bastore;
					dup;
					sspush 383;
					bspush 65;
					bastore;
					dup;
					sspush 385;
					bspush 33;
					bastore;
					dup;
					sspush 386;
					bspush 97;
					bastore;
					dup;
					sspush 387;
					bspush 121;
					bastore;
					dup;
					sspush 388;
					bspush -25;
					bastore;
					dup;
					sspush 389;
					bspush 43;
					bastore;
					dup;
					sspush 390;
					bspush -47;
					bastore;
					dup;
					sspush 391;
					bspush 113;
					bastore;
					dup;
					sspush 392;
					bspush -104;
					bastore;
					dup;
					sspush 393;
					bspush -11;
					bastore;
					dup;
					sspush 394;
					bspush -42;
					bastore;
					dup;
					sspush 395;
					bspush -46;
					bastore;
					dup;
					sspush 396;
					bspush -17;
					bastore;
					dup;
					sspush 397;
					sconst_1;
					bastore;
					dup;
					sspush 398;
					bspush -38;
					bastore;
					dup;
					sspush 399;
					bspush 50;
					bastore;
					dup;
					sspush 400;
					bspush 59;
					bastore;
					dup;
					sspush 401;
					bspush -63;
					bastore;
					dup;
					sspush 402;
					bspush -74;
					bastore;
					dup;
					sspush 403;
					bspush -33;
					bastore;
					dup;
					sspush 404;
					bspush 90;
					bastore;
					dup;
					sspush 405;
					bspush 92;
					bastore;
					dup;
					sspush 406;
					bspush -59;
					bastore;
					dup;
					sspush 407;
					bspush 99;
					bastore;
					dup;
					sspush 408;
					bspush -17;
					bastore;
					dup;
					sspush 409;
					bspush -60;
					bastore;
					dup;
					sspush 410;
					bspush 17;
					bastore;
					dup;
					sspush 411;
					bspush 25;
					bastore;
					dup;
					sspush 412;
					bspush 79;
					bastore;
					dup;
					sspush 413;
					bspush 68;
					bastore;
					dup;
					sspush 414;
					bspush 68;
					bastore;
					dup;
					sspush 415;
					bspush -57;
					bastore;
					dup;
					sspush 416;
					bspush -8;
					bastore;
					dup;
					sspush 417;
					bspush -64;
					bastore;
					dup;
					sspush 418;
					bspush 35;
					bastore;
					dup;
					sspush 419;
					bspush -19;
					bastore;
					dup;
					sspush 420;
					bspush -114;
					bastore;
					dup;
					sspush 421;
					bspush 110;
					bastore;
					dup;
					sspush 422;
					bspush -116;
					bastore;
					dup;
					sspush 423;
					bspush 31;
					bastore;
					dup;
					sspush 424;
					bspush -126;
					bastore;
					dup;
					sspush 425;
					bspush -24;
					bastore;
					dup;
					sspush 426;
					bspush 54;
					bastore;
					dup;
					sspush 427;
					bspush 71;
					bastore;
					dup;
					sspush 428;
					bspush 82;
					bastore;
					dup;
					sspush 429;
					bspush -53;
					bastore;
					dup;
					sspush 430;
					bspush -78;
					bastore;
					dup;
					sspush 431;
					bspush -84;
					bastore;
					dup;
					sspush 432;
					bspush -45;
					bastore;
					dup;
					sspush 433;
					bspush -83;
					bastore;
					dup;
					sspush 434;
					bspush 87;
					bastore;
					dup;
					sspush 435;
					bspush 68;
					bastore;
					dup;
					sspush 436;
					bspush 124;
					bastore;
					dup;
					sspush 437;
					sconst_m1;
					bastore;
					dup;
					sspush 438;
					bspush -128;
					bastore;
					dup;
					sspush 439;
					bspush -49;
					bastore;
					dup;
					sspush 440;
					bspush 124;
					bastore;
					dup;
					sspush 441;
					bspush 103;
					bastore;
					dup;
					sspush 442;
					bspush 28;
					bastore;
					dup;
					sspush 443;
					bspush 56;
					bastore;
					dup;
					sspush 444;
					bspush -114;
					bastore;
					dup;
					sspush 445;
					bspush -10;
					bastore;
					dup;
					sspush 446;
					bspush 97;
					bastore;
					dup;
					sspush 447;
					bspush -78;
					bastore;
					dup;
					sspush 448;
					bspush 54;
					bastore;
					putfield_a 7;		// reference be/msec/smartcard/IdentityCard.certificate
					aload_0;
					sspush 500;
					newarray 11;
					dup;
					sconst_0;
					sconst_1;
					bastore;
					dup;
					sconst_1;
					sconst_2;
					bastore;
					dup;
					sconst_2;
					sconst_3;
					bastore;
					dup;
					sconst_3;
					sconst_4;
					bastore;
					dup;
					sconst_4;
					sconst_5;
					bastore;
					dup;
					sconst_5;
					bspush 6;
					bastore;
					dup;
					bspush 6;
					bspush 7;
					bastore;
					dup;
					bspush 7;
					bspush 8;
					bastore;
					dup;
					bspush 8;
					bspush 9;
					bastore;
					dup;
					bspush 9;
					bspush 10;
					bastore;
					dup;
					bspush 10;
					bspush 11;
					bastore;
					dup;
					bspush 11;
					bspush 12;
					bastore;
					dup;
					bspush 12;
					bspush 13;
					bastore;
					dup;
					bspush 13;
					bspush 14;
					bastore;
					dup;
					bspush 14;
					bspush 15;
					bastore;
					dup;
					bspush 15;
					bspush 16;
					bastore;
					dup;
					bspush 16;
					bspush 17;
					bastore;
					dup;
					bspush 17;
					bspush 18;
					bastore;
					dup;
					bspush 18;
					bspush 19;
					bastore;
					dup;
					bspush 19;
					bspush 20;
					bastore;
					dup;
					bspush 20;
					bspush 21;
					bastore;
					dup;
					bspush 21;
					bspush 22;
					bastore;
					dup;
					bspush 22;
					bspush 23;
					bastore;
					dup;
					bspush 23;
					bspush 24;
					bastore;
					dup;
					bspush 24;
					bspush 25;
					bastore;
					dup;
					bspush 25;
					bspush 26;
					bastore;
					dup;
					bspush 26;
					bspush 27;
					bastore;
					dup;
					bspush 27;
					bspush 28;
					bastore;
					dup;
					bspush 28;
					bspush 29;
					bastore;
					dup;
					bspush 29;
					bspush 30;
					bastore;
					dup;
					bspush 30;
					bspush 31;
					bastore;
					dup;
					bspush 31;
					bspush 32;
					bastore;
					dup;
					bspush 32;
					bspush 33;
					bastore;
					dup;
					bspush 33;
					bspush 34;
					bastore;
					dup;
					bspush 34;
					bspush 35;
					bastore;
					dup;
					bspush 35;
					bspush 36;
					bastore;
					dup;
					bspush 36;
					bspush 37;
					bastore;
					dup;
					bspush 37;
					bspush 38;
					bastore;
					dup;
					bspush 38;
					bspush 39;
					bastore;
					dup;
					bspush 39;
					bspush 40;
					bastore;
					dup;
					bspush 40;
					bspush 41;
					bastore;
					dup;
					bspush 41;
					bspush 42;
					bastore;
					dup;
					bspush 42;
					bspush 43;
					bastore;
					dup;
					bspush 43;
					bspush 44;
					bastore;
					dup;
					bspush 44;
					bspush 45;
					bastore;
					dup;
					bspush 45;
					bspush 46;
					bastore;
					dup;
					bspush 46;
					bspush 47;
					bastore;
					dup;
					bspush 47;
					bspush 48;
					bastore;
					dup;
					bspush 48;
					bspush 49;
					bastore;
					dup;
					bspush 49;
					bspush 50;
					bastore;
					dup;
					bspush 50;
					bspush 51;
					bastore;
					dup;
					bspush 51;
					bspush 52;
					bastore;
					dup;
					bspush 52;
					bspush 53;
					bastore;
					dup;
					bspush 53;
					bspush 54;
					bastore;
					dup;
					bspush 54;
					bspush 55;
					bastore;
					dup;
					bspush 55;
					bspush 56;
					bastore;
					dup;
					bspush 56;
					bspush 57;
					bastore;
					dup;
					bspush 57;
					bspush 58;
					bastore;
					dup;
					bspush 58;
					bspush 59;
					bastore;
					dup;
					bspush 59;
					bspush 60;
					bastore;
					dup;
					bspush 60;
					bspush 61;
					bastore;
					dup;
					bspush 61;
					bspush 62;
					bastore;
					dup;
					bspush 62;
					bspush 63;
					bastore;
					dup;
					bspush 63;
					bspush 64;
					bastore;
					dup;
					bspush 64;
					bspush 65;
					bastore;
					dup;
					bspush 65;
					bspush 66;
					bastore;
					dup;
					bspush 66;
					bspush 67;
					bastore;
					dup;
					bspush 67;
					bspush 68;
					bastore;
					dup;
					bspush 68;
					bspush 69;
					bastore;
					dup;
					bspush 69;
					bspush 70;
					bastore;
					dup;
					bspush 70;
					bspush 71;
					bastore;
					dup;
					bspush 71;
					bspush 72;
					bastore;
					dup;
					bspush 72;
					bspush 73;
					bastore;
					dup;
					bspush 73;
					bspush 74;
					bastore;
					dup;
					bspush 74;
					bspush 75;
					bastore;
					dup;
					bspush 75;
					bspush 76;
					bastore;
					dup;
					bspush 76;
					bspush 77;
					bastore;
					dup;
					bspush 77;
					bspush 78;
					bastore;
					dup;
					bspush 78;
					bspush 79;
					bastore;
					dup;
					bspush 79;
					bspush 80;
					bastore;
					dup;
					bspush 80;
					bspush 81;
					bastore;
					dup;
					bspush 81;
					bspush 82;
					bastore;
					dup;
					bspush 82;
					bspush 83;
					bastore;
					dup;
					bspush 83;
					bspush 84;
					bastore;
					dup;
					bspush 84;
					bspush 85;
					bastore;
					dup;
					bspush 85;
					bspush 86;
					bastore;
					dup;
					bspush 86;
					bspush 87;
					bastore;
					dup;
					bspush 87;
					bspush 88;
					bastore;
					dup;
					bspush 88;
					bspush 89;
					bastore;
					dup;
					bspush 89;
					bspush 90;
					bastore;
					dup;
					bspush 90;
					bspush 91;
					bastore;
					dup;
					bspush 91;
					bspush 92;
					bastore;
					dup;
					bspush 92;
					bspush 93;
					bastore;
					dup;
					bspush 93;
					bspush 94;
					bastore;
					dup;
					bspush 94;
					bspush 95;
					bastore;
					dup;
					bspush 95;
					bspush 96;
					bastore;
					dup;
					bspush 96;
					bspush 97;
					bastore;
					dup;
					bspush 97;
					bspush 98;
					bastore;
					dup;
					bspush 98;
					bspush 99;
					bastore;
					dup;
					bspush 99;
					bspush 100;
					bastore;
					dup;
					bspush 100;
					bspush 101;
					bastore;
					dup;
					bspush 101;
					bspush 102;
					bastore;
					dup;
					bspush 102;
					bspush 103;
					bastore;
					dup;
					bspush 103;
					bspush 104;
					bastore;
					dup;
					bspush 104;
					bspush 105;
					bastore;
					dup;
					bspush 105;
					bspush 106;
					bastore;
					dup;
					bspush 106;
					bspush 107;
					bastore;
					dup;
					bspush 107;
					bspush 108;
					bastore;
					dup;
					bspush 108;
					bspush 109;
					bastore;
					dup;
					bspush 109;
					bspush 110;
					bastore;
					dup;
					bspush 110;
					bspush 111;
					bastore;
					dup;
					bspush 111;
					bspush 112;
					bastore;
					dup;
					bspush 112;
					bspush 113;
					bastore;
					dup;
					bspush 113;
					bspush 114;
					bastore;
					dup;
					bspush 114;
					bspush 115;
					bastore;
					dup;
					bspush 115;
					bspush 116;
					bastore;
					dup;
					bspush 116;
					bspush 117;
					bastore;
					dup;
					bspush 117;
					bspush 118;
					bastore;
					dup;
					bspush 118;
					bspush 119;
					bastore;
					dup;
					bspush 119;
					bspush 120;
					bastore;
					dup;
					bspush 120;
					bspush 121;
					bastore;
					dup;
					bspush 121;
					bspush 122;
					bastore;
					dup;
					bspush 122;
					bspush 123;
					bastore;
					dup;
					bspush 123;
					bspush 124;
					bastore;
					dup;
					bspush 124;
					bspush 125;
					bastore;
					dup;
					bspush 125;
					bspush 126;
					bastore;
					dup;
					bspush 126;
					bspush 127;
					bastore;
					dup;
					bspush 127;
					bspush -128;
					bastore;
					dup;
					sspush 128;
					bspush -127;
					bastore;
					dup;
					sspush 129;
					bspush -126;
					bastore;
					dup;
					sspush 130;
					bspush -125;
					bastore;
					dup;
					sspush 131;
					bspush -124;
					bastore;
					dup;
					sspush 132;
					bspush -123;
					bastore;
					dup;
					sspush 133;
					bspush -122;
					bastore;
					dup;
					sspush 134;
					bspush -121;
					bastore;
					dup;
					sspush 135;
					bspush -120;
					bastore;
					dup;
					sspush 136;
					bspush -119;
					bastore;
					dup;
					sspush 137;
					bspush -118;
					bastore;
					dup;
					sspush 138;
					bspush -117;
					bastore;
					dup;
					sspush 139;
					bspush -116;
					bastore;
					dup;
					sspush 140;
					bspush -115;
					bastore;
					dup;
					sspush 141;
					bspush -114;
					bastore;
					dup;
					sspush 142;
					bspush -113;
					bastore;
					dup;
					sspush 143;
					bspush -112;
					bastore;
					dup;
					sspush 144;
					bspush -111;
					bastore;
					dup;
					sspush 145;
					bspush -110;
					bastore;
					dup;
					sspush 146;
					bspush -109;
					bastore;
					dup;
					sspush 147;
					bspush -108;
					bastore;
					dup;
					sspush 148;
					bspush -107;
					bastore;
					dup;
					sspush 149;
					bspush -106;
					bastore;
					dup;
					sspush 150;
					bspush -105;
					bastore;
					dup;
					sspush 151;
					bspush -104;
					bastore;
					dup;
					sspush 152;
					bspush -103;
					bastore;
					dup;
					sspush 153;
					bspush -102;
					bastore;
					dup;
					sspush 154;
					bspush -101;
					bastore;
					dup;
					sspush 155;
					bspush -100;
					bastore;
					dup;
					sspush 156;
					bspush -99;
					bastore;
					dup;
					sspush 157;
					bspush -98;
					bastore;
					dup;
					sspush 158;
					bspush -97;
					bastore;
					dup;
					sspush 159;
					bspush -96;
					bastore;
					dup;
					sspush 160;
					bspush -95;
					bastore;
					dup;
					sspush 161;
					bspush -94;
					bastore;
					dup;
					sspush 162;
					bspush -93;
					bastore;
					dup;
					sspush 163;
					bspush -92;
					bastore;
					dup;
					sspush 164;
					bspush -91;
					bastore;
					dup;
					sspush 165;
					bspush -90;
					bastore;
					dup;
					sspush 166;
					bspush -89;
					bastore;
					dup;
					sspush 167;
					bspush -88;
					bastore;
					dup;
					sspush 168;
					bspush -87;
					bastore;
					dup;
					sspush 169;
					bspush -86;
					bastore;
					dup;
					sspush 170;
					bspush -85;
					bastore;
					dup;
					sspush 171;
					bspush -84;
					bastore;
					dup;
					sspush 172;
					bspush -83;
					bastore;
					dup;
					sspush 173;
					bspush -82;
					bastore;
					dup;
					sspush 174;
					bspush -81;
					bastore;
					dup;
					sspush 175;
					bspush -80;
					bastore;
					dup;
					sspush 176;
					bspush -79;
					bastore;
					dup;
					sspush 177;
					bspush -78;
					bastore;
					dup;
					sspush 178;
					bspush -77;
					bastore;
					dup;
					sspush 179;
					bspush -76;
					bastore;
					dup;
					sspush 180;
					bspush -75;
					bastore;
					dup;
					sspush 181;
					bspush -74;
					bastore;
					dup;
					sspush 182;
					bspush -73;
					bastore;
					dup;
					sspush 183;
					bspush -72;
					bastore;
					dup;
					sspush 184;
					bspush -71;
					bastore;
					dup;
					sspush 185;
					bspush -70;
					bastore;
					dup;
					sspush 186;
					bspush -69;
					bastore;
					dup;
					sspush 187;
					bspush -68;
					bastore;
					dup;
					sspush 188;
					bspush -67;
					bastore;
					dup;
					sspush 189;
					bspush -66;
					bastore;
					dup;
					sspush 190;
					bspush -65;
					bastore;
					dup;
					sspush 191;
					bspush -64;
					bastore;
					dup;
					sspush 192;
					bspush -63;
					bastore;
					dup;
					sspush 193;
					bspush -62;
					bastore;
					dup;
					sspush 194;
					bspush -61;
					bastore;
					dup;
					sspush 195;
					bspush -60;
					bastore;
					dup;
					sspush 196;
					bspush -59;
					bastore;
					dup;
					sspush 197;
					bspush -58;
					bastore;
					dup;
					sspush 198;
					bspush -57;
					bastore;
					dup;
					sspush 199;
					bspush -56;
					bastore;
					dup;
					sspush 200;
					bspush -55;
					bastore;
					dup;
					sspush 201;
					bspush -54;
					bastore;
					dup;
					sspush 202;
					bspush -53;
					bastore;
					dup;
					sspush 203;
					bspush -52;
					bastore;
					dup;
					sspush 204;
					bspush -51;
					bastore;
					dup;
					sspush 205;
					bspush -50;
					bastore;
					dup;
					sspush 206;
					bspush -49;
					bastore;
					dup;
					sspush 207;
					bspush -48;
					bastore;
					dup;
					sspush 208;
					bspush -47;
					bastore;
					dup;
					sspush 209;
					bspush -46;
					bastore;
					dup;
					sspush 210;
					bspush -45;
					bastore;
					dup;
					sspush 211;
					bspush -44;
					bastore;
					dup;
					sspush 212;
					bspush -43;
					bastore;
					dup;
					sspush 213;
					bspush -42;
					bastore;
					dup;
					sspush 214;
					bspush -41;
					bastore;
					dup;
					sspush 215;
					bspush -40;
					bastore;
					dup;
					sspush 216;
					bspush -39;
					bastore;
					dup;
					sspush 217;
					bspush -38;
					bastore;
					dup;
					sspush 218;
					bspush -37;
					bastore;
					dup;
					sspush 219;
					bspush -36;
					bastore;
					dup;
					sspush 220;
					bspush -35;
					bastore;
					dup;
					sspush 221;
					bspush -34;
					bastore;
					dup;
					sspush 222;
					bspush -33;
					bastore;
					dup;
					sspush 223;
					bspush -32;
					bastore;
					dup;
					sspush 224;
					bspush -31;
					bastore;
					dup;
					sspush 225;
					bspush -30;
					bastore;
					dup;
					sspush 226;
					bspush -29;
					bastore;
					dup;
					sspush 227;
					bspush -28;
					bastore;
					dup;
					sspush 228;
					bspush -27;
					bastore;
					dup;
					sspush 229;
					bspush -26;
					bastore;
					dup;
					sspush 230;
					bspush -25;
					bastore;
					dup;
					sspush 231;
					bspush -24;
					bastore;
					dup;
					sspush 232;
					bspush -23;
					bastore;
					dup;
					sspush 233;
					bspush -22;
					bastore;
					dup;
					sspush 234;
					bspush -21;
					bastore;
					dup;
					sspush 235;
					bspush -20;
					bastore;
					dup;
					sspush 236;
					bspush -19;
					bastore;
					dup;
					sspush 237;
					bspush -18;
					bastore;
					dup;
					sspush 238;
					bspush -17;
					bastore;
					dup;
					sspush 239;
					bspush -16;
					bastore;
					dup;
					sspush 240;
					bspush -15;
					bastore;
					dup;
					sspush 241;
					bspush -14;
					bastore;
					dup;
					sspush 242;
					bspush -13;
					bastore;
					dup;
					sspush 243;
					bspush -12;
					bastore;
					dup;
					sspush 244;
					bspush -11;
					bastore;
					dup;
					sspush 245;
					bspush -10;
					bastore;
					dup;
					sspush 246;
					bspush -9;
					bastore;
					dup;
					sspush 247;
					bspush -8;
					bastore;
					dup;
					sspush 248;
					bspush -7;
					bastore;
					dup;
					sspush 249;
					bspush -6;
					bastore;
					dup;
					sspush 250;
					bspush -5;
					bastore;
					dup;
					sspush 251;
					bspush -4;
					bastore;
					dup;
					sspush 252;
					bspush -3;
					bastore;
					dup;
					sspush 253;
					bspush -2;
					bastore;
					dup;
					sspush 254;
					sconst_m1;
					bastore;
					dup;
					sspush 256;
					sconst_1;
					bastore;
					dup;
					sspush 257;
					sconst_2;
					bastore;
					dup;
					sspush 258;
					sconst_3;
					bastore;
					dup;
					sspush 259;
					sconst_4;
					bastore;
					dup;
					sspush 260;
					sconst_5;
					bastore;
					dup;
					sspush 261;
					bspush 6;
					bastore;
					dup;
					sspush 262;
					bspush 7;
					bastore;
					dup;
					sspush 263;
					bspush 8;
					bastore;
					dup;
					sspush 264;
					bspush 9;
					bastore;
					dup;
					sspush 265;
					bspush 10;
					bastore;
					dup;
					sspush 266;
					bspush 11;
					bastore;
					dup;
					sspush 267;
					bspush 12;
					bastore;
					dup;
					sspush 268;
					bspush 13;
					bastore;
					dup;
					sspush 269;
					bspush 14;
					bastore;
					dup;
					sspush 270;
					bspush 15;
					bastore;
					dup;
					sspush 271;
					bspush 16;
					bastore;
					dup;
					sspush 272;
					bspush 17;
					bastore;
					dup;
					sspush 273;
					bspush 18;
					bastore;
					dup;
					sspush 274;
					bspush 19;
					bastore;
					dup;
					sspush 275;
					bspush 20;
					bastore;
					dup;
					sspush 276;
					bspush 21;
					bastore;
					dup;
					sspush 277;
					bspush 22;
					bastore;
					dup;
					sspush 278;
					bspush 23;
					bastore;
					dup;
					sspush 279;
					bspush 24;
					bastore;
					dup;
					sspush 280;
					bspush 25;
					bastore;
					dup;
					sspush 281;
					bspush 26;
					bastore;
					dup;
					sspush 282;
					bspush 27;
					bastore;
					dup;
					sspush 283;
					bspush 28;
					bastore;
					dup;
					sspush 284;
					bspush 29;
					bastore;
					dup;
					sspush 285;
					bspush 30;
					bastore;
					dup;
					sspush 286;
					bspush 31;
					bastore;
					dup;
					sspush 287;
					bspush 32;
					bastore;
					dup;
					sspush 288;
					bspush 33;
					bastore;
					dup;
					sspush 289;
					bspush 34;
					bastore;
					dup;
					sspush 290;
					bspush 35;
					bastore;
					dup;
					sspush 291;
					bspush 36;
					bastore;
					dup;
					sspush 292;
					bspush 37;
					bastore;
					dup;
					sspush 293;
					bspush 38;
					bastore;
					dup;
					sspush 294;
					bspush 39;
					bastore;
					dup;
					sspush 295;
					bspush 40;
					bastore;
					dup;
					sspush 296;
					bspush 41;
					bastore;
					dup;
					sspush 297;
					bspush 42;
					bastore;
					dup;
					sspush 298;
					bspush 43;
					bastore;
					dup;
					sspush 299;
					bspush 44;
					bastore;
					dup;
					sspush 300;
					bspush 45;
					bastore;
					dup;
					sspush 301;
					bspush 46;
					bastore;
					dup;
					sspush 302;
					bspush 47;
					bastore;
					dup;
					sspush 303;
					bspush 48;
					bastore;
					dup;
					sspush 304;
					bspush 49;
					bastore;
					dup;
					sspush 305;
					bspush 50;
					bastore;
					dup;
					sspush 306;
					bspush 51;
					bastore;
					dup;
					sspush 307;
					bspush 52;
					bastore;
					dup;
					sspush 308;
					bspush 53;
					bastore;
					dup;
					sspush 309;
					bspush 54;
					bastore;
					dup;
					sspush 310;
					bspush 55;
					bastore;
					dup;
					sspush 311;
					bspush 56;
					bastore;
					dup;
					sspush 312;
					bspush 57;
					bastore;
					dup;
					sspush 313;
					bspush 58;
					bastore;
					dup;
					sspush 314;
					bspush 59;
					bastore;
					dup;
					sspush 315;
					bspush 60;
					bastore;
					dup;
					sspush 316;
					bspush 61;
					bastore;
					dup;
					sspush 317;
					bspush 62;
					bastore;
					dup;
					sspush 318;
					bspush 63;
					bastore;
					dup;
					sspush 319;
					bspush 64;
					bastore;
					dup;
					sspush 320;
					bspush 65;
					bastore;
					dup;
					sspush 321;
					bspush 66;
					bastore;
					dup;
					sspush 322;
					bspush 67;
					bastore;
					dup;
					sspush 323;
					bspush 68;
					bastore;
					dup;
					sspush 324;
					bspush 69;
					bastore;
					dup;
					sspush 325;
					bspush 70;
					bastore;
					dup;
					sspush 326;
					bspush 71;
					bastore;
					dup;
					sspush 327;
					bspush 72;
					bastore;
					dup;
					sspush 328;
					bspush 73;
					bastore;
					dup;
					sspush 329;
					bspush 74;
					bastore;
					dup;
					sspush 330;
					bspush 75;
					bastore;
					dup;
					sspush 331;
					bspush 76;
					bastore;
					dup;
					sspush 332;
					bspush 77;
					bastore;
					dup;
					sspush 333;
					bspush 78;
					bastore;
					dup;
					sspush 334;
					bspush 79;
					bastore;
					dup;
					sspush 335;
					bspush 80;
					bastore;
					dup;
					sspush 336;
					bspush 81;
					bastore;
					dup;
					sspush 337;
					bspush 82;
					bastore;
					dup;
					sspush 338;
					bspush 83;
					bastore;
					dup;
					sspush 339;
					bspush 84;
					bastore;
					dup;
					sspush 340;
					bspush 85;
					bastore;
					dup;
					sspush 341;
					bspush 86;
					bastore;
					dup;
					sspush 342;
					bspush 87;
					bastore;
					dup;
					sspush 343;
					bspush 88;
					bastore;
					dup;
					sspush 344;
					bspush 89;
					bastore;
					dup;
					sspush 345;
					bspush 90;
					bastore;
					dup;
					sspush 346;
					bspush 91;
					bastore;
					dup;
					sspush 347;
					bspush 92;
					bastore;
					dup;
					sspush 348;
					bspush 93;
					bastore;
					dup;
					sspush 349;
					bspush 94;
					bastore;
					dup;
					sspush 350;
					bspush 95;
					bastore;
					dup;
					sspush 351;
					bspush 96;
					bastore;
					dup;
					sspush 352;
					bspush 97;
					bastore;
					dup;
					sspush 353;
					bspush 98;
					bastore;
					dup;
					sspush 354;
					bspush 99;
					bastore;
					dup;
					sspush 355;
					bspush 100;
					bastore;
					dup;
					sspush 356;
					bspush 101;
					bastore;
					dup;
					sspush 357;
					bspush 102;
					bastore;
					dup;
					sspush 358;
					bspush 103;
					bastore;
					dup;
					sspush 359;
					bspush 104;
					bastore;
					dup;
					sspush 360;
					bspush 105;
					bastore;
					dup;
					sspush 361;
					bspush 106;
					bastore;
					dup;
					sspush 362;
					bspush 107;
					bastore;
					dup;
					sspush 363;
					bspush 108;
					bastore;
					dup;
					sspush 364;
					bspush 109;
					bastore;
					dup;
					sspush 365;
					bspush 110;
					bastore;
					dup;
					sspush 366;
					bspush 111;
					bastore;
					dup;
					sspush 367;
					bspush 112;
					bastore;
					dup;
					sspush 368;
					bspush 113;
					bastore;
					dup;
					sspush 369;
					bspush 114;
					bastore;
					dup;
					sspush 370;
					bspush 115;
					bastore;
					dup;
					sspush 371;
					bspush 116;
					bastore;
					dup;
					sspush 372;
					bspush 117;
					bastore;
					dup;
					sspush 373;
					bspush 118;
					bastore;
					dup;
					sspush 374;
					bspush 119;
					bastore;
					dup;
					sspush 375;
					bspush 120;
					bastore;
					dup;
					sspush 376;
					bspush 121;
					bastore;
					dup;
					sspush 377;
					bspush 122;
					bastore;
					dup;
					sspush 378;
					bspush 123;
					bastore;
					dup;
					sspush 379;
					bspush 124;
					bastore;
					dup;
					sspush 380;
					bspush 125;
					bastore;
					dup;
					sspush 381;
					bspush 126;
					bastore;
					dup;
					sspush 382;
					bspush 127;
					bastore;
					dup;
					sspush 383;
					bspush -128;
					bastore;
					dup;
					sspush 384;
					bspush -127;
					bastore;
					dup;
					sspush 385;
					bspush -126;
					bastore;
					dup;
					sspush 386;
					bspush -125;
					bastore;
					dup;
					sspush 387;
					bspush -124;
					bastore;
					dup;
					sspush 388;
					bspush -123;
					bastore;
					dup;
					sspush 389;
					bspush -122;
					bastore;
					dup;
					sspush 390;
					bspush -121;
					bastore;
					dup;
					sspush 391;
					bspush -120;
					bastore;
					dup;
					sspush 392;
					bspush -119;
					bastore;
					dup;
					sspush 393;
					bspush -118;
					bastore;
					dup;
					sspush 394;
					bspush -117;
					bastore;
					dup;
					sspush 395;
					bspush -116;
					bastore;
					dup;
					sspush 396;
					bspush -115;
					bastore;
					dup;
					sspush 397;
					bspush -114;
					bastore;
					dup;
					sspush 398;
					bspush -113;
					bastore;
					dup;
					sspush 399;
					bspush -112;
					bastore;
					dup;
					sspush 400;
					bspush -111;
					bastore;
					dup;
					sspush 401;
					bspush -110;
					bastore;
					dup;
					sspush 402;
					bspush -109;
					bastore;
					dup;
					sspush 403;
					bspush -108;
					bastore;
					dup;
					sspush 404;
					bspush -107;
					bastore;
					dup;
					sspush 405;
					bspush -106;
					bastore;
					dup;
					sspush 406;
					bspush -105;
					bastore;
					dup;
					sspush 407;
					bspush -104;
					bastore;
					dup;
					sspush 408;
					bspush -103;
					bastore;
					dup;
					sspush 409;
					bspush -102;
					bastore;
					dup;
					sspush 410;
					bspush -101;
					bastore;
					dup;
					sspush 411;
					bspush -100;
					bastore;
					dup;
					sspush 412;
					bspush -99;
					bastore;
					dup;
					sspush 413;
					bspush -98;
					bastore;
					dup;
					sspush 414;
					bspush -97;
					bastore;
					dup;
					sspush 415;
					bspush -96;
					bastore;
					dup;
					sspush 416;
					bspush -95;
					bastore;
					dup;
					sspush 417;
					bspush -94;
					bastore;
					dup;
					sspush 418;
					bspush -93;
					bastore;
					dup;
					sspush 419;
					bspush -92;
					bastore;
					dup;
					sspush 420;
					bspush -91;
					bastore;
					dup;
					sspush 421;
					bspush -90;
					bastore;
					dup;
					sspush 422;
					bspush -89;
					bastore;
					dup;
					sspush 423;
					bspush -88;
					bastore;
					dup;
					sspush 424;
					bspush -87;
					bastore;
					dup;
					sspush 425;
					bspush -86;
					bastore;
					dup;
					sspush 426;
					bspush -85;
					bastore;
					dup;
					sspush 427;
					bspush -84;
					bastore;
					dup;
					sspush 428;
					bspush -83;
					bastore;
					dup;
					sspush 429;
					bspush -82;
					bastore;
					dup;
					sspush 430;
					bspush -81;
					bastore;
					dup;
					sspush 431;
					bspush -80;
					bastore;
					dup;
					sspush 432;
					bspush -79;
					bastore;
					dup;
					sspush 433;
					bspush -78;
					bastore;
					dup;
					sspush 434;
					bspush -77;
					bastore;
					dup;
					sspush 435;
					bspush -76;
					bastore;
					dup;
					sspush 436;
					bspush -75;
					bastore;
					dup;
					sspush 437;
					bspush -74;
					bastore;
					dup;
					sspush 438;
					bspush -73;
					bastore;
					dup;
					sspush 439;
					bspush -72;
					bastore;
					dup;
					sspush 440;
					bspush -71;
					bastore;
					dup;
					sspush 441;
					bspush -70;
					bastore;
					dup;
					sspush 442;
					bspush -69;
					bastore;
					dup;
					sspush 443;
					bspush -68;
					bastore;
					dup;
					sspush 444;
					bspush -67;
					bastore;
					dup;
					sspush 445;
					bspush -66;
					bastore;
					dup;
					sspush 446;
					bspush -65;
					bastore;
					dup;
					sspush 447;
					bspush -64;
					bastore;
					dup;
					sspush 448;
					bspush -63;
					bastore;
					dup;
					sspush 449;
					bspush -62;
					bastore;
					dup;
					sspush 450;
					bspush -61;
					bastore;
					dup;
					sspush 451;
					bspush -60;
					bastore;
					dup;
					sspush 452;
					bspush -59;
					bastore;
					dup;
					sspush 453;
					bspush -58;
					bastore;
					dup;
					sspush 454;
					bspush -57;
					bastore;
					dup;
					sspush 455;
					bspush -56;
					bastore;
					dup;
					sspush 456;
					bspush -55;
					bastore;
					dup;
					sspush 457;
					bspush -54;
					bastore;
					dup;
					sspush 458;
					bspush -53;
					bastore;
					dup;
					sspush 459;
					bspush -52;
					bastore;
					dup;
					sspush 460;
					bspush -51;
					bastore;
					dup;
					sspush 461;
					bspush -50;
					bastore;
					dup;
					sspush 462;
					bspush -49;
					bastore;
					dup;
					sspush 463;
					bspush -48;
					bastore;
					dup;
					sspush 464;
					bspush -47;
					bastore;
					dup;
					sspush 465;
					bspush -46;
					bastore;
					dup;
					sspush 466;
					bspush -45;
					bastore;
					dup;
					sspush 467;
					bspush -44;
					bastore;
					dup;
					sspush 468;
					bspush -43;
					bastore;
					dup;
					sspush 469;
					bspush -42;
					bastore;
					dup;
					sspush 470;
					bspush -41;
					bastore;
					dup;
					sspush 471;
					bspush -40;
					bastore;
					dup;
					sspush 472;
					bspush -39;
					bastore;
					dup;
					sspush 473;
					bspush -38;
					bastore;
					dup;
					sspush 474;
					bspush -37;
					bastore;
					dup;
					sspush 475;
					bspush -36;
					bastore;
					dup;
					sspush 476;
					bspush -35;
					bastore;
					dup;
					sspush 477;
					bspush -34;
					bastore;
					dup;
					sspush 478;
					bspush -33;
					bastore;
					dup;
					sspush 479;
					bspush -32;
					bastore;
					dup;
					sspush 480;
					bspush -31;
					bastore;
					dup;
					sspush 481;
					bspush -30;
					bastore;
					dup;
					sspush 482;
					bspush -29;
					bastore;
					dup;
					sspush 483;
					bspush -28;
					bastore;
					dup;
					sspush 484;
					bspush -27;
					bastore;
					dup;
					sspush 485;
					bspush -26;
					bastore;
					dup;
					sspush 486;
					bspush -25;
					bastore;
					dup;
					sspush 487;
					bspush -24;
					bastore;
					dup;
					sspush 488;
					bspush -23;
					bastore;
					dup;
					sspush 489;
					bspush -22;
					bastore;
					dup;
					sspush 490;
					bspush -21;
					bastore;
					dup;
					sspush 491;
					bspush -20;
					bastore;
					dup;
					sspush 492;
					bspush -19;
					bastore;
					dup;
					sspush 493;
					bspush -18;
					bastore;
					dup;
					sspush 494;
					bspush -17;
					bastore;
					dup;
					sspush 495;
					bspush -16;
					bastore;
					dup;
					sspush 496;
					bspush -15;
					bastore;
					dup;
					sspush 497;
					bspush -14;
					bastore;
					dup;
					sspush 498;
					bspush -13;
					bastore;
					dup;
					sspush 499;
					bspush -12;
					bastore;
					putfield_a 8;		// reference be/msec/smartcard/IdentityCard.bigdata
					aload_0;
					bspush 10;
					newarray 11;
					dup;
					sconst_0;
					sconst_1;
					bastore;
					dup;
					sconst_1;
					sconst_2;
					bastore;
					dup;
					sconst_2;
					sconst_3;
					bastore;
					dup;
					sconst_3;
					sconst_4;
					bastore;
					dup;
					sconst_4;
					sconst_5;
					bastore;
					dup;
					sconst_5;
					bspush 6;
					bastore;
					dup;
					bspush 6;
					bspush 7;
					bastore;
					dup;
					bspush 7;
					bspush 8;
					bastore;
					dup;
					bspush 8;
					bspush 9;
					bastore;
					dup;
					bspush 9;
					bspush 10;
					bastore;
					putfield_a 9;		// reference be/msec/smartcard/IdentityCard.smalldata
					aload_0;
					sconst_2;
					newarray 11;
					dup;
					sconst_0;
					sconst_1;
					bastore;
					dup;
					sconst_1;
					sconst_2;
					bastore;
					putfield_a 10;		// reference be/msec/smartcard/IdentityCard.verysmalldata
					aload_0;
					sspush 294;
					newarray 11;
					dup;
					sconst_0;
					bspush 48;
					bastore;
					dup;
					sconst_1;
					bspush -126;
					bastore;
					dup;
					sconst_2;
					sconst_1;
					bastore;
					dup;
					sconst_3;
					bspush 34;
					bastore;
					dup;
					sconst_4;
					bspush 48;
					bastore;
					dup;
					sconst_5;
					bspush 13;
					bastore;
					dup;
					bspush 6;
					bspush 6;
					bastore;
					dup;
					bspush 7;
					bspush 9;
					bastore;
					dup;
					bspush 8;
					bspush 42;
					bastore;
					dup;
					bspush 9;
					bspush -122;
					bastore;
					dup;
					bspush 10;
					bspush 72;
					bastore;
					dup;
					bspush 11;
					bspush -122;
					bastore;
					dup;
					bspush 12;
					bspush -9;
					bastore;
					dup;
					bspush 13;
					bspush 13;
					bastore;
					dup;
					bspush 14;
					sconst_1;
					bastore;
					dup;
					bspush 15;
					sconst_1;
					bastore;
					dup;
					bspush 16;
					sconst_1;
					bastore;
					dup;
					bspush 17;
					sconst_5;
					bastore;
					dup;
					bspush 19;
					sconst_3;
					bastore;
					dup;
					bspush 20;
					bspush -126;
					bastore;
					dup;
					bspush 21;
					sconst_1;
					bastore;
					dup;
					bspush 22;
					bspush 15;
					bastore;
					dup;
					bspush 24;
					bspush 48;
					bastore;
					dup;
					bspush 25;
					bspush -126;
					bastore;
					dup;
					bspush 26;
					sconst_1;
					bastore;
					dup;
					bspush 27;
					bspush 10;
					bastore;
					dup;
					bspush 28;
					sconst_2;
					bastore;
					dup;
					bspush 29;
					bspush -126;
					bastore;
					dup;
					bspush 30;
					sconst_1;
					bastore;
					dup;
					bspush 31;
					sconst_1;
					bastore;
					dup;
					bspush 33;
					bspush -102;
					bastore;
					dup;
					bspush 34;
					bspush 38;
					bastore;
					dup;
					bspush 35;
					bspush 76;
					bastore;
					dup;
					bspush 36;
					bspush -92;
					bastore;
					dup;
					bspush 37;
					bspush 68;
					bastore;
					dup;
					bspush 38;
					bspush 120;
					bastore;
					dup;
					bspush 39;
					bspush 16;
					bastore;
					dup;
					bspush 40;
					bspush -121;
					bastore;
					dup;
					bspush 41;
					bspush 117;
					bastore;
					dup;
					bspush 42;
					bspush 80;
					bastore;
					dup;
					bspush 43;
					bspush -121;
					bastore;
					dup;
					bspush 44;
					bspush 38;
					bastore;
					dup;
					bspush 45;
					bspush -42;
					bastore;
					dup;
					bspush 46;
					bspush 39;
					bastore;
					dup;
					bspush 47;
					bspush -71;
					bastore;
					dup;
					bspush 48;
					bspush 41;
					bastore;
					dup;
					bspush 49;
					bspush 14;
					bastore;
					dup;
					bspush 50;
					bspush 45;
					bastore;
					dup;
					bspush 51;
					bspush 63;
					bastore;
					dup;
					bspush 52;
					bspush 17;
					bastore;
					dup;
					bspush 53;
					bspush -30;
					bastore;
					dup;
					bspush 54;
					bspush 20;
					bastore;
					dup;
					bspush 55;
					bspush -106;
					bastore;
					dup;
					bspush 56;
					bspush -117;
					bastore;
					dup;
					bspush 57;
					bspush -15;
					bastore;
					dup;
					bspush 58;
					bspush 82;
					bastore;
					dup;
					bspush 59;
					bspush -87;
					bastore;
					dup;
					bspush 60;
					bspush -117;
					bastore;
					dup;
					bspush 61;
					bspush -77;
					bastore;
					dup;
					bspush 62;
					bspush -38;
					bastore;
					dup;
					bspush 63;
					bspush 67;
					bastore;
					dup;
					bspush 64;
					bspush -25;
					bastore;
					dup;
					bspush 65;
					bspush -39;
					bastore;
					dup;
					bspush 66;
					bspush -105;
					bastore;
					dup;
					bspush 67;
					bspush 46;
					bastore;
					dup;
					bspush 68;
					bspush -116;
					bastore;
					dup;
					bspush 69;
					bspush -76;
					bastore;
					dup;
					bspush 70;
					bspush 125;
					bastore;
					dup;
					bspush 71;
					bspush -111;
					bastore;
					dup;
					bspush 72;
					bspush 99;
					bastore;
					dup;
					bspush 73;
					bspush -48;
					bastore;
					dup;
					bspush 74;
					bspush -45;
					bastore;
					dup;
					bspush 75;
					bspush 7;
					bastore;
					dup;
					bspush 76;
					bspush 23;
					bastore;
					dup;
					bspush 77;
					bspush 102;
					bastore;
					dup;
					bspush 78;
					bspush -10;
					bastore;
					dup;
					bspush 79;
					bspush -78;
					bastore;
					dup;
					bspush 80;
					bspush 119;
					bastore;
					dup;
					bspush 81;
					bspush -69;
					bastore;
					dup;
					bspush 82;
					bspush 45;
					bastore;
					dup;
					bspush 83;
					bspush 70;
					bastore;
					dup;
					bspush 84;
					bspush -92;
					bastore;
					dup;
					bspush 85;
					bspush -90;
					bastore;
					dup;
					bspush 86;
					bspush -83;
					bastore;
					dup;
					bspush 87;
					bspush 116;
					bastore;
					dup;
					bspush 89;
					bspush -54;
					bastore;
					dup;
					bspush 90;
					bspush 67;
					bastore;
					dup;
					bspush 91;
					bspush -46;
					bastore;
					dup;
					bspush 92;
					bspush -65;
					bastore;
					dup;
					bspush 93;
					bspush 24;
					bastore;
					dup;
					bspush 94;
					bspush -118;
					bastore;
					dup;
					bspush 95;
					bspush -71;
					bastore;
					dup;
					bspush 96;
					bspush -32;
					bastore;
					dup;
					bspush 97;
					bspush 120;
					bastore;
					dup;
					bspush 98;
					bspush 62;
					bastore;
					dup;
					bspush 99;
					sconst_3;
					bastore;
					dup;
					bspush 100;
					bspush -60;
					bastore;
					dup;
					bspush 101;
					bspush 96;
					bastore;
					dup;
					bspush 102;
					bspush -91;
					bastore;
					dup;
					bspush 103;
					bspush -55;
					bastore;
					dup;
					bspush 104;
					bspush 116;
					bastore;
					dup;
					bspush 105;
					bspush -36;
					bastore;
					dup;
					bspush 106;
					bspush -58;
					bastore;
					dup;
					bspush 107;
					bspush -120;
					bastore;
					dup;
					bspush 108;
					bspush 76;
					bastore;
					dup;
					bspush 109;
					bspush 34;
					bastore;
					dup;
					bspush 110;
					bspush -37;
					bastore;
					dup;
					bspush 111;
					bspush -75;
					bastore;
					dup;
					bspush 112;
					bspush -16;
					bastore;
					dup;
					bspush 113;
					bspush 106;
					bastore;
					dup;
					bspush 114;
					bspush 61;
					bastore;
					dup;
					bspush 115;
					bspush -28;
					bastore;
					dup;
					bspush 116;
					bspush -16;
					bastore;
					dup;
					bspush 117;
					bspush 57;
					bastore;
					dup;
					bspush 118;
					bspush 59;
					bastore;
					dup;
					bspush 119;
					bspush 112;
					bastore;
					dup;
					bspush 120;
					bspush -106;
					bastore;
					dup;
					bspush 121;
					bspush 12;
					bastore;
					dup;
					bspush 122;
					bspush 107;
					bastore;
					dup;
					bspush 123;
					sconst_1;
					bastore;
					dup;
					bspush 124;
					bspush 123;
					bastore;
					dup;
					bspush 125;
					bspush -88;
					bastore;
					dup;
					bspush 126;
					bspush -35;
					bastore;
					dup;
					bspush 127;
					bspush 30;
					bastore;
					dup;
					sspush 128;
					bspush -114;
					bastore;
					dup;
					sspush 129;
					bspush 71;
					bastore;
					dup;
					sspush 130;
					bspush 59;
					bastore;
					dup;
					sspush 131;
					bspush -112;
					bastore;
					dup;
					sspush 132;
					bspush 26;
					bastore;
					dup;
					sspush 133;
					bspush -52;
					bastore;
					dup;
					sspush 134;
					bspush -33;
					bastore;
					dup;
					sspush 135;
					bspush -116;
					bastore;
					dup;
					sspush 136;
					bspush -35;
					bastore;
					dup;
					sspush 137;
					bspush -34;
					bastore;
					dup;
					sspush 138;
					bspush -111;
					bastore;
					dup;
					sspush 139;
					bspush -34;
					bastore;
					dup;
					sspush 140;
					bspush -74;
					bastore;
					dup;
					sspush 141;
					bspush -92;
					bastore;
					dup;
					sspush 142;
					bspush -47;
					bastore;
					dup;
					sspush 143;
					bspush 103;
					bastore;
					dup;
					sspush 144;
					bspush -79;
					bastore;
					dup;
					sspush 145;
					bspush 19;
					bastore;
					dup;
					sspush 146;
					bspush -28;
					bastore;
					dup;
					sspush 147;
					bspush 124;
					bastore;
					dup;
					sspush 148;
					bspush -66;
					bastore;
					dup;
					sspush 149;
					bspush 28;
					bastore;
					dup;
					sspush 150;
					bspush -14;
					bastore;
					dup;
					sspush 151;
					bspush -98;
					bastore;
					dup;
					sspush 152;
					bspush 104;
					bastore;
					dup;
					sspush 153;
					bspush -96;
					bastore;
					dup;
					sspush 154;
					bspush -10;
					bastore;
					dup;
					sspush 155;
					bspush 60;
					bastore;
					dup;
					sspush 156;
					sconst_2;
					bastore;
					dup;
					sspush 157;
					bspush 18;
					bastore;
					dup;
					sspush 158;
					bspush -4;
					bastore;
					dup;
					sspush 159;
					bspush 16;
					bastore;
					dup;
					sspush 160;
					bspush 108;
					bastore;
					dup;
					sspush 161;
					bspush 59;
					bastore;
					dup;
					sspush 162;
					bspush 26;
					bastore;
					dup;
					sspush 163;
					bspush -59;
					bastore;
					dup;
					sspush 164;
					bspush 106;
					bastore;
					dup;
					sspush 166;
					bspush 48;
					bastore;
					dup;
					sspush 167;
					bspush 36;
					bastore;
					dup;
					sspush 168;
					bspush -12;
					bastore;
					dup;
					sspush 169;
					bspush -114;
					bastore;
					dup;
					sspush 170;
					bspush 90;
					bastore;
					dup;
					sspush 171;
					bspush -27;
					bastore;
					dup;
					sspush 172;
					bspush 122;
					bastore;
					dup;
					sspush 173;
					bspush 107;
					bastore;
					dup;
					sspush 174;
					bspush -107;
					bastore;
					dup;
					sspush 175;
					bspush 17;
					bastore;
					dup;
					sspush 176;
					bspush -75;
					bastore;
					dup;
					sspush 177;
					bspush 18;
					bastore;
					dup;
					sspush 178;
					bspush -52;
					bastore;
					dup;
					sspush 179;
					bspush -29;
					bastore;
					dup;
					sspush 180;
					bspush -22;
					bastore;
					dup;
					sspush 182;
					bspush -32;
					bastore;
					dup;
					sspush 183;
					bspush -10;
					bastore;
					dup;
					sspush 184;
					bspush 87;
					bastore;
					dup;
					sspush 185;
					bspush 116;
					bastore;
					dup;
					sspush 186;
					bspush 89;
					bastore;
					dup;
					sspush 187;
					bspush 47;
					bastore;
					dup;
					sspush 188;
					bspush -116;
					bastore;
					dup;
					sspush 189;
					bspush -127;
					bastore;
					dup;
					sspush 190;
					bspush 19;
					bastore;
					dup;
					sspush 191;
					bspush -110;
					bastore;
					dup;
					sspush 192;
					bspush 53;
					bastore;
					dup;
					sspush 193;
					bspush 63;
					bastore;
					dup;
					sspush 194;
					bspush -72;
					bastore;
					dup;
					sspush 195;
					bspush 101;
					bastore;
					dup;
					sspush 196;
					bspush 76;
					bastore;
					dup;
					sspush 197;
					bspush -2;
					bastore;
					dup;
					sspush 198;
					bspush 117;
					bastore;
					dup;
					sspush 199;
					bspush 64;
					bastore;
					dup;
					sspush 201;
					bspush 126;
					bastore;
					dup;
					sspush 202;
					bspush -2;
					bastore;
					dup;
					sspush 203;
					sconst_1;
					bastore;
					dup;
					sspush 204;
					bspush 56;
					bastore;
					dup;
					sspush 205;
					bspush 90;
					bastore;
					dup;
					sspush 206;
					bspush -25;
					bastore;
					dup;
					sspush 207;
					bspush -6;
					bastore;
					dup;
					sspush 208;
					bspush -11;
					bastore;
					dup;
					sspush 209;
					bspush 44;
					bastore;
					dup;
					sspush 210;
					bspush 117;
					bastore;
					dup;
					sspush 211;
					bspush 78;
					bastore;
					dup;
					sspush 212;
					bspush 73;
					bastore;
					dup;
					sspush 213;
					bspush -87;
					bastore;
					dup;
					sspush 214;
					bspush -39;
					bastore;
					dup;
					sspush 215;
					bspush -31;
					bastore;
					dup;
					sspush 216;
					bspush 100;
					bastore;
					dup;
					sspush 217;
					bspush -93;
					bastore;
					dup;
					sspush 218;
					bspush -122;
					bastore;
					dup;
					sspush 219;
					bspush 19;
					bastore;
					dup;
					sspush 220;
					bspush -113;
					bastore;
					dup;
					sspush 221;
					bspush 44;
					bastore;
					dup;
					sspush 222;
					bspush 83;
					bastore;
					dup;
					sspush 223;
					bspush -38;
					bastore;
					dup;
					sspush 224;
					bspush -57;
					bastore;
					dup;
					sspush 225;
					bspush 45;
					bastore;
					dup;
					sspush 226;
					bspush 75;
					bastore;
					dup;
					sspush 227;
					bspush 52;
					bastore;
					dup;
					sspush 228;
					bspush -104;
					bastore;
					dup;
					sspush 229;
					bspush 69;
					bastore;
					dup;
					sspush 230;
					bspush -6;
					bastore;
					dup;
					sspush 231;
					bspush 103;
					bastore;
					dup;
					sspush 232;
					bspush 104;
					bastore;
					dup;
					sspush 233;
					bspush -100;
					bastore;
					dup;
					sspush 234;
					bspush -44;
					bastore;
					dup;
					sspush 235;
					bspush 57;
					bastore;
					dup;
					sspush 236;
					bspush 79;
					bastore;
					dup;
					sspush 237;
					bspush -99;
					bastore;
					dup;
					sspush 238;
					bspush -108;
					bastore;
					dup;
					sspush 239;
					bspush -68;
					bastore;
					dup;
					sspush 240;
					bspush -11;
					bastore;
					dup;
					sspush 241;
					bspush -27;
					bastore;
					dup;
					sspush 242;
					bspush 115;
					bastore;
					dup;
					sspush 243;
					bspush 15;
					bastore;
					dup;
					sspush 244;
					bspush -107;
					bastore;
					dup;
					sspush 245;
					bspush 87;
					bastore;
					dup;
					sspush 246;
					bspush 6;
					bastore;
					dup;
					sspush 247;
					bspush 8;
					bastore;
					dup;
					sspush 248;
					bspush -94;
					bastore;
					dup;
					sspush 249;
					bspush 76;
					bastore;
					dup;
					sspush 250;
					bspush 124;
					bastore;
					dup;
					sspush 251;
					bspush 11;
					bastore;
					dup;
					sspush 252;
					bspush 6;
					bastore;
					dup;
					sspush 253;
					bspush 35;
					bastore;
					dup;
					sspush 254;
					bspush -6;
					bastore;
					dup;
					sspush 255;
					bspush 46;
					bastore;
					dup;
					sspush 256;
					bspush -115;
					bastore;
					dup;
					sspush 257;
					bspush 37;
					bastore;
					dup;
					sspush 258;
					bspush -62;
					bastore;
					dup;
					sspush 259;
					sconst_5;
					bastore;
					dup;
					sspush 260;
					bspush 70;
					bastore;
					dup;
					sspush 261;
					bspush 11;
					bastore;
					dup;
					sspush 262;
					bspush 99;
					bastore;
					dup;
					sspush 263;
					bspush -51;
					bastore;
					dup;
					sspush 264;
					bspush -4;
					bastore;
					dup;
					sspush 265;
					bspush -102;
					bastore;
					dup;
					sspush 266;
					bspush -51;
					bastore;
					dup;
					sspush 267;
					bspush 127;
					bastore;
					dup;
					sspush 268;
					bspush -87;
					bastore;
					dup;
					sspush 269;
					bspush 77;
					bastore;
					dup;
					sspush 270;
					bspush -112;
					bastore;
					dup;
					sspush 271;
					bspush 43;
					bastore;
					dup;
					sspush 272;
					bspush -125;
					bastore;
					dup;
					sspush 273;
					sconst_m1;
					bastore;
					dup;
					sspush 274;
					bspush 101;
					bastore;
					dup;
					sspush 275;
					bspush -128;
					bastore;
					dup;
					sspush 276;
					bspush 8;
					bastore;
					dup;
					sspush 277;
					bspush -63;
					bastore;
					dup;
					sspush 278;
					bspush 92;
					bastore;
					dup;
					sspush 279;
					bspush 49;
					bastore;
					dup;
					sspush 280;
					bspush -78;
					bastore;
					dup;
					sspush 281;
					bspush -92;
					bastore;
					dup;
					sspush 282;
					bspush -101;
					bastore;
					dup;
					sspush 283;
					bspush 35;
					bastore;
					dup;
					sspush 284;
					bspush -63;
					bastore;
					dup;
					sspush 285;
					bspush 86;
					bastore;
					dup;
					sspush 286;
					bspush -36;
					bastore;
					dup;
					sspush 287;
					bspush 126;
					bastore;
					dup;
					sspush 288;
					bspush -3;
					bastore;
					dup;
					sspush 289;
					sconst_2;
					bastore;
					dup;
					sspush 290;
					sconst_3;
					bastore;
					dup;
					sspush 291;
					sconst_1;
					bastore;
					dup;
					sspush 293;
					sconst_1;
					bastore;
					putfield_a 11;		// reference be/msec/smartcard/IdentityCard.PKg
					aload_0;
					sspush 136;
					newarray 11;
					dup;
					sconst_0;
					sconst_1;
					bastore;
					dup;
					sconst_2;
					sconst_1;
					bastore;
					dup;
					sconst_4;
					bspush -119;
					bastore;
					dup;
					sconst_5;
					bspush 13;
					bastore;
					dup;
					bspush 6;
					bspush -113;
					bastore;
					dup;
					bspush 7;
					bspush 13;
					bastore;
					dup;
					bspush 8;
					bspush 45;
					bastore;
					dup;
					bspush 9;
					bspush -34;
					bastore;
					dup;
					bspush 10;
					bspush 81;
					bastore;
					dup;
					bspush 11;
					bspush -34;
					bastore;
					dup;
					bspush 12;
					bspush -85;
					bastore;
					dup;
					bspush 13;
					bspush -49;
					bastore;
					dup;
					bspush 14;
					bspush 111;
					bastore;
					dup;
					bspush 15;
					bspush -55;
					bastore;
					dup;
					bspush 16;
					bspush 72;
					bastore;
					dup;
					bspush 17;
					bspush 80;
					bastore;
					dup;
					bspush 18;
					bspush 45;
					bastore;
					dup;
					bspush 19;
					bspush 109;
					bastore;
					dup;
					bspush 20;
					bspush 23;
					bastore;
					dup;
					bspush 21;
					bspush -34;
					bastore;
					dup;
					bspush 22;
					bspush 86;
					bastore;
					dup;
					bspush 23;
					bspush 87;
					bastore;
					dup;
					bspush 24;
					bspush 119;
					bastore;
					dup;
					bspush 25;
					bspush -116;
					bastore;
					dup;
					bspush 26;
					bspush -109;
					bastore;
					dup;
					bspush 27;
					bspush 30;
					bastore;
					dup;
					bspush 28;
					bspush -91;
					bastore;
					dup;
					bspush 29;
					bspush 59;
					bastore;
					dup;
					bspush 30;
					bspush 24;
					bastore;
					dup;
					bspush 31;
					bspush 59;
					bastore;
					dup;
					bspush 32;
					bspush -82;
					bastore;
					dup;
					bspush 33;
					bspush 103;
					bastore;
					dup;
					bspush 34;
					bspush -125;
					bastore;
					dup;
					bspush 35;
					bspush -70;
					bastore;
					dup;
					bspush 36;
					bspush -46;
					bastore;
					dup;
					bspush 37;
					sconst_3;
					bastore;
					dup;
					bspush 38;
					bspush 116;
					bastore;
					dup;
					bspush 39;
					bspush 103;
					bastore;
					dup;
					bspush 40;
					bspush -63;
					bastore;
					dup;
					bspush 41;
					bspush -36;
					bastore;
					dup;
					bspush 42;
					bspush -94;
					bastore;
					dup;
					bspush 43;
					bspush 59;
					bastore;
					dup;
					bspush 44;
					bspush -5;
					bastore;
					dup;
					bspush 45;
					bspush 32;
					bastore;
					dup;
					bspush 46;
					bspush -68;
					bastore;
					dup;
					bspush 47;
					bspush -3;
					bastore;
					dup;
					bspush 48;
					bspush -29;
					bastore;
					dup;
					bspush 49;
					bspush -80;
					bastore;
					dup;
					bspush 50;
					bspush -41;
					bastore;
					dup;
					bspush 51;
					bspush -106;
					bastore;
					dup;
					bspush 52;
					bspush -23;
					bastore;
					dup;
					bspush 53;
					bspush -40;
					bastore;
					dup;
					bspush 54;
					bspush -23;
					bastore;
					dup;
					bspush 55;
					bspush 35;
					bastore;
					dup;
					bspush 56;
					bspush -18;
					bastore;
					dup;
					bspush 57;
					bspush -121;
					bastore;
					dup;
					bspush 58;
					bspush -72;
					bastore;
					dup;
					bspush 59;
					bspush -53;
					bastore;
					dup;
					bspush 60;
					bspush 31;
					bastore;
					dup;
					bspush 61;
					bspush 59;
					bastore;
					dup;
					bspush 62;
					bspush -50;
					bastore;
					dup;
					bspush 63;
					bspush 89;
					bastore;
					dup;
					bspush 64;
					bspush 127;
					bastore;
					dup;
					bspush 65;
					bspush -46;
					bastore;
					dup;
					bspush 66;
					bspush -109;
					bastore;
					dup;
					bspush 67;
					bspush -91;
					bastore;
					dup;
					bspush 68;
					bspush 101;
					bastore;
					dup;
					bspush 69;
					bspush 16;
					bastore;
					dup;
					bspush 70;
					bspush -13;
					bastore;
					dup;
					bspush 71;
					bspush 41;
					bastore;
					dup;
					bspush 72;
					bspush 82;
					bastore;
					dup;
					bspush 73;
					bspush 35;
					bastore;
					dup;
					bspush 74;
					bspush -59;
					bastore;
					dup;
					bspush 75;
					bspush 101;
					bastore;
					dup;
					bspush 76;
					bspush -89;
					bastore;
					dup;
					bspush 77;
					bspush 66;
					bastore;
					dup;
					bspush 78;
					sconst_3;
					bastore;
					dup;
					bspush 79;
					bspush -59;
					bastore;
					dup;
					bspush 80;
					bspush -45;
					bastore;
					dup;
					bspush 81;
					bspush 32;
					bastore;
					dup;
					bspush 82;
					bspush -118;
					bastore;
					dup;
					bspush 83;
					bspush -76;
					bastore;
					dup;
					bspush 84;
					bspush -103;
					bastore;
					dup;
					bspush 85;
					bspush 21;
					bastore;
					dup;
					bspush 86;
					bspush 69;
					bastore;
					dup;
					bspush 87;
					bspush -97;
					bastore;
					dup;
					bspush 88;
					bspush -102;
					bastore;
					dup;
					bspush 89;
					bspush -58;
					bastore;
					dup;
					bspush 90;
					bspush -82;
					bastore;
					dup;
					bspush 91;
					bspush 112;
					bastore;
					dup;
					bspush 92;
					bspush -113;
					bastore;
					dup;
					bspush 93;
					bspush 120;
					bastore;
					dup;
					bspush 94;
					bspush 69;
					bastore;
					dup;
					bspush 95;
					bspush -101;
					bastore;
					dup;
					bspush 96;
					bspush -119;
					bastore;
					dup;
					bspush 97;
					bspush 98;
					bastore;
					dup;
					bspush 98;
					bspush -41;
					bastore;
					dup;
					bspush 99;
					bspush -126;
					bastore;
					dup;
					bspush 100;
					bspush -103;
					bastore;
					dup;
					bspush 101;
					bspush 25;
					bastore;
					dup;
					bspush 102;
					bspush -109;
					bastore;
					dup;
					bspush 103;
					bspush -63;
					bastore;
					dup;
					bspush 104;
					bspush -108;
					bastore;
					dup;
					bspush 105;
					bspush 34;
					bastore;
					dup;
					bspush 106;
					bspush 61;
					bastore;
					dup;
					bspush 107;
					bspush 39;
					bastore;
					dup;
					bspush 108;
					bspush 56;
					bastore;
					dup;
					bspush 109;
					bspush 76;
					bastore;
					dup;
					bspush 110;
					bspush 127;
					bastore;
					dup;
					bspush 111;
					bspush -90;
					bastore;
					dup;
					bspush 112;
					bspush 29;
					bastore;
					dup;
					bspush 113;
					bspush -95;
					bastore;
					dup;
					bspush 114;
					bspush -40;
					bastore;
					dup;
					bspush 115;
					bspush 7;
					bastore;
					dup;
					bspush 116;
					bspush 96;
					bastore;
					dup;
					bspush 117;
					bspush -20;
					bastore;
					dup;
					bspush 118;
					bspush -35;
					bastore;
					dup;
					bspush 119;
					bspush 65;
					bastore;
					dup;
					bspush 120;
					bspush 119;
					bastore;
					dup;
					bspush 121;
					bspush 49;
					bastore;
					dup;
					bspush 122;
					bspush 91;
					bastore;
					dup;
					bspush 123;
					bspush 99;
					bastore;
					dup;
					bspush 124;
					bspush 98;
					bastore;
					dup;
					bspush 125;
					bspush 66;
					bastore;
					dup;
					bspush 126;
					bspush -25;
					bastore;
					dup;
					bspush 127;
					bspush -15;
					bastore;
					dup;
					sspush 128;
					bspush 41;
					bastore;
					dup;
					sspush 129;
					bspush -14;
					bastore;
					dup;
					sspush 130;
					bspush -62;
					bastore;
					dup;
					sspush 131;
					sconst_5;
					bastore;
					dup;
					sspush 132;
					bspush 108;
					bastore;
					dup;
					sspush 133;
					bspush -110;
					bastore;
					dup;
					sspush 134;
					bspush 37;
					bastore;
					dup;
					sspush 135;
					bspush -95;
					bastore;
					putfield_a 12;		// reference be/msec/smartcard/IdentityCard.commonCertificate
					aload_0;
					bspush 64;
					newarray 11;
					dup;
					sconst_0;
					bspush 81;
					bastore;
					dup;
					sconst_1;
					bspush -47;
					bastore;
					dup;
					sconst_2;
					bspush -61;
					bastore;
					dup;
					sconst_3;
					bspush 102;
					bastore;
					dup;
					sconst_4;
					bspush 21;
					bastore;
					dup;
					sconst_5;
					bspush -51;
					bastore;
					dup;
					bspush 6;
					bspush 20;
					bastore;
					dup;
					bspush 7;
					bspush -55;
					bastore;
					dup;
					bspush 8;
					bspush 63;
					bastore;
					dup;
					bspush 9;
					bspush 126;
					bastore;
					dup;
					bspush 10;
					bspush -34;
					bastore;
					dup;
					bspush 11;
					bspush 120;
					bastore;
					dup;
					bspush 12;
					bspush -90;
					bastore;
					dup;
					bspush 13;
					bspush -16;
					bastore;
					dup;
					bspush 14;
					bspush 30;
					bastore;
					dup;
					bspush 15;
					bspush -66;
					bastore;
					dup;
					bspush 16;
					bspush 115;
					bastore;
					dup;
					bspush 17;
					bspush 50;
					bastore;
					dup;
					bspush 18;
					bspush 108;
					bastore;
					dup;
					bspush 19;
					bspush 15;
					bastore;
					dup;
					bspush 20;
					bspush 89;
					bastore;
					dup;
					bspush 21;
					bspush -78;
					bastore;
					dup;
					bspush 22;
					bspush -107;
					bastore;
					dup;
					bspush 23;
					bspush -98;
					bastore;
					dup;
					bspush 24;
					sconst_4;
					bastore;
					dup;
					bspush 25;
					bspush -4;
					bastore;
					dup;
					bspush 26;
					bspush -117;
					bastore;
					dup;
					bspush 27;
					bspush -110;
					bastore;
					dup;
					bspush 28;
					bspush 13;
					bastore;
					dup;
					bspush 29;
					bspush -93;
					bastore;
					dup;
					bspush 30;
					bspush -124;
					bastore;
					dup;
					bspush 31;
					bspush -77;
					bastore;
					dup;
					bspush 32;
					bspush 34;
					bastore;
					dup;
					bspush 33;
					bspush -59;
					bastore;
					dup;
					bspush 34;
					bspush 37;
					bastore;
					dup;
					bspush 35;
					bspush 45;
					bastore;
					dup;
					bspush 36;
					bspush 62;
					bastore;
					dup;
					bspush 37;
					bspush -81;
					bastore;
					dup;
					bspush 38;
					bspush 31;
					bastore;
					dup;
					bspush 39;
					bspush 98;
					bastore;
					dup;
					bspush 40;
					bspush -118;
					bastore;
					dup;
					bspush 41;
					bspush -7;
					bastore;
					dup;
					bspush 42;
					bspush -114;
					bastore;
					dup;
					bspush 43;
					bspush -20;
					bastore;
					dup;
					bspush 44;
					bspush -66;
					bastore;
					dup;
					bspush 45;
					bspush 93;
					bastore;
					dup;
					bspush 46;
					bspush -32;
					bastore;
					dup;
					bspush 47;
					bspush 101;
					bastore;
					dup;
					bspush 48;
					bspush -27;
					bastore;
					dup;
					bspush 49;
					bspush -4;
					bastore;
					dup;
					bspush 50;
					bspush 86;
					bastore;
					dup;
					bspush 51;
					bspush -29;
					bastore;
					dup;
					bspush 52;
					bspush -79;
					bastore;
					dup;
					bspush 53;
					bspush 24;
					bastore;
					dup;
					bspush 54;
					bspush 38;
					bastore;
					dup;
					bspush 55;
					bspush -21;
					bastore;
					dup;
					bspush 56;
					bspush -104;
					bastore;
					dup;
					bspush 57;
					bspush -10;
					bastore;
					dup;
					bspush 58;
					bspush -18;
					bastore;
					dup;
					bspush 59;
					bspush -5;
					bastore;
					dup;
					bspush 60;
					bspush 84;
					bastore;
					dup;
					bspush 61;
					bspush 77;
					bastore;
					dup;
					bspush 62;
					bspush -2;
					bastore;
					dup;
					bspush 63;
					bspush 125;
					bastore;
					putfield_a 13;		// reference be/msec/smartcard/IdentityCard.privExp_ComCer
					aload_0;
					bspush 64;
					newarray 11;
					dup;
					sconst_0;
					bspush -119;
					bastore;
					dup;
					sconst_1;
					bspush 13;
					bastore;
					dup;
					sconst_2;
					bspush -113;
					bastore;
					dup;
					sconst_3;
					bspush 13;
					bastore;
					dup;
					sconst_4;
					bspush 45;
					bastore;
					dup;
					sconst_5;
					bspush -34;
					bastore;
					dup;
					bspush 6;
					bspush 81;
					bastore;
					dup;
					bspush 7;
					bspush -34;
					bastore;
					dup;
					bspush 8;
					bspush -85;
					bastore;
					dup;
					bspush 9;
					bspush -49;
					bastore;
					dup;
					bspush 10;
					bspush 111;
					bastore;
					dup;
					bspush 11;
					bspush -55;
					bastore;
					dup;
					bspush 12;
					bspush 72;
					bastore;
					dup;
					bspush 13;
					bspush 80;
					bastore;
					dup;
					bspush 14;
					bspush 45;
					bastore;
					dup;
					bspush 15;
					bspush 109;
					bastore;
					dup;
					bspush 16;
					bspush 23;
					bastore;
					dup;
					bspush 17;
					bspush -34;
					bastore;
					dup;
					bspush 18;
					bspush 86;
					bastore;
					dup;
					bspush 19;
					bspush 87;
					bastore;
					dup;
					bspush 20;
					bspush 119;
					bastore;
					dup;
					bspush 21;
					bspush -116;
					bastore;
					dup;
					bspush 22;
					bspush -109;
					bastore;
					dup;
					bspush 23;
					bspush 30;
					bastore;
					dup;
					bspush 24;
					bspush -91;
					bastore;
					dup;
					bspush 25;
					bspush 59;
					bastore;
					dup;
					bspush 26;
					bspush 24;
					bastore;
					dup;
					bspush 27;
					bspush 59;
					bastore;
					dup;
					bspush 28;
					bspush -82;
					bastore;
					dup;
					bspush 29;
					bspush 103;
					bastore;
					dup;
					bspush 30;
					bspush -125;
					bastore;
					dup;
					bspush 31;
					bspush -70;
					bastore;
					dup;
					bspush 32;
					bspush -46;
					bastore;
					dup;
					bspush 33;
					sconst_3;
					bastore;
					dup;
					bspush 34;
					bspush 116;
					bastore;
					dup;
					bspush 35;
					bspush 103;
					bastore;
					dup;
					bspush 36;
					bspush -63;
					bastore;
					dup;
					bspush 37;
					bspush -36;
					bastore;
					dup;
					bspush 38;
					bspush -94;
					bastore;
					dup;
					bspush 39;
					bspush 59;
					bastore;
					dup;
					bspush 40;
					bspush -5;
					bastore;
					dup;
					bspush 41;
					bspush 32;
					bastore;
					dup;
					bspush 42;
					bspush -68;
					bastore;
					dup;
					bspush 43;
					bspush -3;
					bastore;
					dup;
					bspush 44;
					bspush -29;
					bastore;
					dup;
					bspush 45;
					bspush -80;
					bastore;
					dup;
					bspush 46;
					bspush -41;
					bastore;
					dup;
					bspush 47;
					bspush -106;
					bastore;
					dup;
					bspush 48;
					bspush -23;
					bastore;
					dup;
					bspush 49;
					bspush -40;
					bastore;
					dup;
					bspush 50;
					bspush -23;
					bastore;
					dup;
					bspush 51;
					bspush 35;
					bastore;
					dup;
					bspush 52;
					bspush -18;
					bastore;
					dup;
					bspush 53;
					bspush -121;
					bastore;
					dup;
					bspush 54;
					bspush -72;
					bastore;
					dup;
					bspush 55;
					bspush -53;
					bastore;
					dup;
					bspush 56;
					bspush 31;
					bastore;
					dup;
					bspush 57;
					bspush 59;
					bastore;
					dup;
					bspush 58;
					bspush -50;
					bastore;
					dup;
					bspush 59;
					bspush 89;
					bastore;
					dup;
					bspush 60;
					bspush 127;
					bastore;
					dup;
					bspush 61;
					bspush -46;
					bastore;
					dup;
					bspush 62;
					bspush -109;
					bastore;
					dup;
					bspush 63;
					bspush -91;
					bastore;
					putfield_a 14;		// reference be/msec/smartcard/IdentityCard.privMod_ComCer
					aload_0;
					sconst_3;
					newarray 11;
					dup;
					sconst_0;
					bspush 74;
					bastore;
					dup;
					sconst_1;
					bspush 97;
					bastore;
					dup;
					sconst_2;
					bspush 110;
					bastore;
					putfield_a 15;		// reference be/msec/smartcard/IdentityCard.serial
					aload_0;
					bspush 12;
					newarray 11;
					dup;
					sconst_0;
					bspush 74;
					bastore;
					dup;
					sconst_1;
					bspush 97;
					bastore;
					dup;
					sconst_2;
					bspush 110;
					bastore;
					dup;
					sconst_3;
					bspush 32;
					bastore;
					dup;
					sconst_4;
					bspush 86;
					bastore;
					dup;
					sconst_5;
					bspush 111;
					bastore;
					dup;
					bspush 6;
					bspush 115;
					bastore;
					dup;
					bspush 7;
					bspush 115;
					bastore;
					dup;
					bspush 8;
					bspush 97;
					bastore;
					dup;
					bspush 9;
					bspush 101;
					bastore;
					dup;
					bspush 10;
					bspush 114;
					bastore;
					dup;
					bspush 11;
					bspush 116;
					bastore;
					putfield_a 16;		// reference be/msec/smartcard/IdentityCard.name
					aload_0;
					sconst_0;
					putfield_s 17;		// short be/msec/smartcard/IdentityCard.offset
					aload_0;
					bspush 64;
					putfield_s 18;		// short be/msec/smartcard/IdentityCard.keySizeInBytes
					aload_0;
					sspush 512;
					putfield_s 19;		// short be/msec/smartcard/IdentityCard.keySizeInBits
					aload_0;
					aconst_null;
					putfield_a 20;		// reference be/msec/smartcard/IdentityCard.privKey
					aload_0;
					sconst_0;
					putfield_b 21;		// boolean be/msec/smartcard/IdentityCard.auth
					aload_0;
					new 29;		// javacard/framework/OwnerPIN
					dup;
					sconst_3;
					sconst_4;
					invokespecial 32;		// javacard/framework/OwnerPIN.<init>(BB)V
					putfield_a 22;		// reference be/msec/smartcard/IdentityCard.pin
					getfield_a_this 22;		// reference be/msec/smartcard/IdentityCard.pin
					sconst_4;
					newarray 11;
					dup;
					sconst_0;
					bspush 49;
					bastore;
					dup;
					sconst_1;
					bspush 50;
					bastore;
					dup;
					sconst_2;
					bspush 51;
					bastore;
					dup;
					sconst_3;
					bspush 52;
					bastore;
					sconst_0;
					sconst_4;
					invokevirtual 62;		// update([BSB)V
					aload_0;
					sconst_5;
					getfield_s_this 19;		// short be/msec/smartcard/IdentityCard.keySizeInBits
					sconst_0;
					invokestatic 64;		// javacard/security/KeyBuilder.buildKey(BSZ)Ljavacard/security/Key;
					checkcast 0 28;		// T_CLASSORINTERFACE javacard/security/RSAPrivateKey
					putfield_a 20;		// reference be/msec/smartcard/IdentityCard.privKey
					getfield_a_this 20;		// reference be/msec/smartcard/IdentityCard.privKey
					getfield_a_this 1;		// reference be/msec/smartcard/IdentityCard.privExponent
					getfield_s_this 17;		// short be/msec/smartcard/IdentityCard.offset
					getfield_s_this 18;		// short be/msec/smartcard/IdentityCard.keySizeInBytes
					invokeinterface 4 28 6;		// javacard/security/RSAPrivateKey
					getfield_a_this 20;		// reference be/msec/smartcard/IdentityCard.privKey
					getfield_a_this 0;		// reference be/msec/smartcard/IdentityCard.privModulus
					getfield_s_this 17;		// short be/msec/smartcard/IdentityCard.offset
					getfield_s_this 18;		// short be/msec/smartcard/IdentityCard.keySizeInBytes
					invokeinterface 4 28 7;		// javacard/security/RSAPrivateKey
					aload_0;
					bspush 8;
					newarray 11;
					putfield_a 23;		// reference be/msec/smartcard/IdentityCard.date
					aload_0;
					invokevirtual 30;		// register()V
					aload_0;
					sconst_1;
					sconst_2;
					invokestatic 31;		// javacard/framework/JCSystem.makeTransientShortArray(SB)[S
					putfield_a 24;		// reference be/msec/smartcard/IdentityCard.BUF_IN_OFFSET
					return;
		}

		.method public static install([BSB)V 0 {
			.stack 1;
			.locals 0;

				L0:	new 33;		// be/msec/smartcard/IdentityCard
					invokespecial 34;		// be/msec/smartcard/IdentityCard.<init>()V
					return;
		}

		.method public select()Z 6 {
			.stack 1;
			.locals 0;

				L0:	getfield_a_this 22;		// reference be/msec/smartcard/IdentityCard.pin
					invokevirtual 35;		// getTriesRemaining()B
					ifne L2;
				L1:	sconst_0;
					sreturn;
				L2:	sconst_1;
					sreturn;
		}

		.method public process(Ljavacard/framework/APDU;)V 7 {
			.stack 2;
			.locals 1;

			.descriptor	Ljavacard/framework/APDU;	0.10;

				L0:	aload_1;
					invokevirtual 37;		// getBuffer()[B
					astore_2;
					aload_0;
					invokevirtual 38;		// selectingApplet()Z
					ifeq L2;
				L1:	return;
				L2:	aload_2;
					sconst_0;
					baload;
					bspush -128;
					if_scmpeq L4;
				L3:	sspush 28160;
					invokestatic 39;		// javacard/framework/ISOException.throwIt(S)V
				L4:	aload_2;
					sconst_1;
					baload;
					stableswitch L14 33 48 L11 L5 L14 L7 L10 L6 L9 L8 L12 L14 L14 L14 L14 L14 L14 L13;
				L5:	aload_0;
					aload_1;
					invokespecial 40;		// be/msec/smartcard/IdentityCard.validatePIN(Ljavacard/framework/APDU;)V
					goto L17;
				L6:	aload_0;
					aload_1;
					invokespecial 41;		// be/msec/smartcard/IdentityCard.getSerial(Ljavacard/framework/APDU;)V
					goto L17;
				L7:	aload_0;
					aload_1;
					invokespecial 42;		// be/msec/smartcard/IdentityCard.getName(Ljavacard/framework/APDU;)V
					goto L17;
				L8:	aload_0;
					aload_1;
					invokespecial 43;		// be/msec/smartcard/IdentityCard.sendCertificate(Ljavacard/framework/APDU;)V
					goto L17;
				L9:	aload_0;
					aload_1;
					invokespecial 44;		// be/msec/smartcard/IdentityCard.sign(Ljavacard/framework/APDU;)V
					goto L17;
				L10:	aload_0;
					aload_1;
					invokespecial 45;		// be/msec/smartcard/IdentityCard.updateTime(Ljavacard/framework/APDU;)V
					goto L17;
				L11:	aload_0;
					aload_1;
					invokespecial 46;		// be/msec/smartcard/IdentityCard.authenticateServiceProvider(Ljavacard/framework/APDU;)V
					goto L17;
				L12:	aload_0;
					aload_1;
					invokespecial 47;		// be/msec/smartcard/IdentityCard.verifyChallenge(Ljavacard/framework/APDU;)V
					goto L17;
				L13:	aload_0;
					aload_1;
					invokespecial 48;		// be/msec/smartcard/IdentityCard.authenticateCard(Ljavacard/framework/APDU;)V
					goto L17;
				L14:	sspush 27904;
					invokestatic 39;		// javacard/framework/ISOException.throwIt(S)V
				L15:	goto L17;
				L16:	pop;
					sspush -30584;
					invokestatic 39;		// javacard/framework/ISOException.throwIt(S)V
				L17:	return;
			.exceptionTable {
				// start_block end_block handler_block catch_type_index
				L0 L1 L16 36;
				L2 L15 L16 36;
			}
		}

		.method private authenticateCard(Ljavacard/framework/APDU;)V {
			.stack 6;
			.locals 3;

			.descriptor	Ljavacard/framework/APDU;	0.10;

				L0:	getfield_b_this 21;		// boolean be/msec/smartcard/IdentityCard.auth
					ifne L2;
				L1:	return;
				L2:	aload_0;
					aload_1;
					invokespecial 49;		// be/msec/smartcard/IdentityCard.receiveBigData(Ljavacard/framework/APDU;)[B
					astore_2;
					bspush 16;
					newarray 11;
					astore_3;
					bspush 13;
					sconst_0;
					invokestatic 50;		// javacardx/crypto/Cipher.getInstance(BZ)Ljavacardx/crypto/Cipher;
					astore 4;
					aload 4;
					getfield_a_this 25;		// reference be/msec/smartcard/IdentityCard.symKey
					sconst_1;
					invokevirtual 52;		// init(Ljavacard/security/Key;B)V
					aload 4;
					aload_2;
					sconst_0;
					aload_2;
					arraylength;
					aload_3;
					sconst_0;
					invokevirtual 53;		// doFinal([BSS[BS)S
					pop;
					return;
		}

		.method private verifyChallenge(Ljavacard/framework/APDU;)V {
			.stack 6;
			.locals 3;

			.descriptor	Ljavacard/framework/APDU;	0.10;

				L0:	aload_0;
					aload_1;
					invokespecial 49;		// be/msec/smartcard/IdentityCard.receiveBigData(Ljavacard/framework/APDU;)[B
					astore_2;
					bspush 16;
					newarray 11;
					astore_3;
					bspush 13;
					sconst_0;
					invokestatic 50;		// javacardx/crypto/Cipher.getInstance(BZ)Ljavacardx/crypto/Cipher;
					astore 4;
					aload 4;
					getfield_a_this 25;		// reference be/msec/smartcard/IdentityCard.symKey
					sconst_1;
					invokevirtual 52;		// init(Ljavacard/security/Key;B)V
					aload 4;
					aload_2;
					sconst_0;
					aload_2;
					arraylength;
					aload_3;
					sconst_0;
					invokevirtual 53;		// doFinal([BSS[BS)S
					pop;
					aload_0;
					sconst_0;
					putfield_b 21;		// boolean be/msec/smartcard/IdentityCard.auth
					return;
		}

		.method private authenticateServiceProvider(Ljavacard/framework/APDU;)V {
			.stack 7;
			.locals 19;

			.descriptor	Ljavacard/framework/APDU;	0.10;

				L0:	aload_0;
					aload_1;
					invokespecial 49;		// be/msec/smartcard/IdentityCard.receiveBigData(Ljavacard/framework/APDU;)[B
					astore_2;
					bspush 64;
					newarray 11;
					astore_3;
					aload_2;
					arraylength;
					aload_3;
					arraylength;
					ssub;
					newarray 11;
					astore 4;
					bspush 8;
					newarray 11;
					astore 5;
					sconst_3;
					newarray 11;
					astore 6;
					bspush 64;
					newarray 11;
					astore 7;
					aload 4;
					arraylength;
					aload 6;
					arraylength;
					ssub;
					aload 7;
					arraylength;
					ssub;
					aload 5;
					arraylength;
					ssub;
					sconst_1;
					ssub;
					newarray 11;
					astore 8;
					bspush 16;
					newarray 11;
					astore 9;
					aload_2;
					sconst_0;
					aload_3;
					sconst_0;
					bspush 64;
					invokestatic 54;		// javacard/framework/Util.arrayCopy([BS[BSS)S
					pop;
					aload_2;
					bspush 64;
					aload 4;
					sconst_0;
					aload_2;
					arraylength;
					bspush 64;
					ssub;
					invokestatic 54;		// javacard/framework/Util.arrayCopy([BS[BSS)S
					pop;
					aload 4;
					sconst_0;
					aload 6;
					sconst_0;
					sconst_3;
					invokestatic 54;		// javacard/framework/Util.arrayCopy([BS[BSS)S
					pop;
					aload 4;
					sconst_4;
					aload 7;
					sconst_0;
					bspush 64;
					invokestatic 54;		// javacard/framework/Util.arrayCopy([BS[BSS)S
					pop;
					aload 4;
					bspush 68;
					aload 5;
					sconst_0;
					bspush 8;
					invokestatic 54;		// javacard/framework/Util.arrayCopy([BS[BSS)S
					pop;
					aload 4;
					bspush 76;
					aload 8;
					sconst_0;
					aload 8;
					arraylength;
					invokestatic 54;		// javacard/framework/Util.arrayCopy([BS[BSS)S
					pop;
					aload 8;
					sconst_0;
					aload 9;
					sconst_0;
					aload 8;
					arraylength;
					invokestatic 54;		// javacard/framework/Util.arrayCopy([BS[BSS)S
					pop;
					bspush 10;
					sconst_0;
					invokestatic 55;		// javacard/security/Signature.getInstance(BZ)Ljavacard/security/Signature;
					astore 10;
				L1:	sconst_4;
					sspush 512;
					sconst_0;
					invokestatic 64;		// javacard/security/KeyBuilder.buildKey(BSZ)Ljavacard/security/Key;
					checkcast 0 56;		// T_CLASSORINTERFACE javacard/security/RSAPublicKey
					astore 11;
					aload 11;
					getfield_a_this 3;		// reference be/msec/smartcard/IdentityCard.pubExp_CA
					getfield_s_this 17;		// short be/msec/smartcard/IdentityCard.offset
					sconst_3;
					invokeinterface 4 56 6;		// javacard/security/RSAPublicKey
					aload 11;
					getfield_a_this 2;		// reference be/msec/smartcard/IdentityCard.pubMod_CA
					getfield_s_this 17;		// short be/msec/smartcard/IdentityCard.offset
					getfield_a_this 2;		// reference be/msec/smartcard/IdentityCard.pubMod_CA
					arraylength;
					invokeinterface 4 56 7;		// javacard/security/RSAPublicKey
					aload 10;
					aload 11;
					sconst_2;
					invokevirtual 57;		// init(Ljavacard/security/Key;B)V
					aload 10;
					aload 4;
					sconst_0;
					aload 4;
					arraylength;
					aload_3;
					sconst_0;
					aload_3;
					arraylength;
					invokevirtual 58;		// verify([BSS[BSS)Z
					sstore 12;
					sload 12;
					ifne L3;
				L2:	sspush -30584;
					invokestatic 39;		// javacard/framework/ISOException.throwIt(S)V
				L3:	aload_0;
					aload 5;
					getfield_a_this 6;		// reference be/msec/smartcard/IdentityCard.lastValidationTime
					invokespecial 59;		// be/msec/smartcard/IdentityCard.isSmaller([B[B)Z
					ifeq L5;
				L4:	sspush -30584;
					invokestatic 39;		// javacard/framework/ISOException.throwIt(S)V
				L5:	aload_0;
					aload_0;
					invokespecial 60;		// be/msec/smartcard/IdentityCard.getSymKey()Ljavacard/security/AESKey;
					putfield_a 25;		// reference be/msec/smartcard/IdentityCard.symKey
					sconst_4;
					sspush 512;
					sconst_0;
					invokestatic 64;		// javacard/security/KeyBuilder.buildKey(BSZ)Ljavacard/security/Key;
					checkcast 0 56;		// T_CLASSORINTERFACE javacard/security/RSAPublicKey
					astore 13;
					aload 13;
					aload 6;
					getfield_s_this 17;		// short be/msec/smartcard/IdentityCard.offset
					sconst_3;
					invokeinterface 4 56 6;		// javacard/security/RSAPublicKey
					aload 13;
					aload 7;
					getfield_s_this 17;		// short be/msec/smartcard/IdentityCard.offset
					aload 7;
					arraylength;
					invokeinterface 4 56 7;		// javacard/security/RSAPublicKey
					bspush 10;
					sconst_0;
					invokestatic 50;		// javacardx/crypto/Cipher.getInstance(BZ)Ljavacardx/crypto/Cipher;
					astore 14;
					bspush 64;
					sconst_2;
					invokestatic 61;		// javacard/framework/JCSystem.makeTransientByteArray(SB)[B
					astore 15;
					aload 14;
					aload 13;
					sconst_2;
					invokevirtual 52;		// init(Ljavacard/security/Key;B)V
				L6:	aload 14;
					getfield_a_this 26;		// reference be/msec/smartcard/IdentityCard.rnd
					sconst_0;
					getfield_a_this 26;		// reference be/msec/smartcard/IdentityCard.rnd
					arraylength;
					aload 15;
					sconst_0;
					invokevirtual 53;		// doFinal([BSS[BS)S
					pop;
				L7:	goto L9;
				L8:	pop;
					sspush -30584;
					invokestatic 39;		// javacard/framework/ISOException.throwIt(S)V
				L9:	aload_0;
					invokespecial 63;		// be/msec/smartcard/IdentityCard.generateRandomBytes()[B
					astore 16;
					aload_0;
					aload 16;
					putfield_a 27;		// reference be/msec/smartcard/IdentityCard.challenge
					bspush 13;
					sconst_0;
					invokestatic 50;		// javacardx/crypto/Cipher.getInstance(BZ)Ljavacardx/crypto/Cipher;
					astore 17;
					aload 17;
					getfield_a_this 25;		// reference be/msec/smartcard/IdentityCard.symKey
					sconst_2;
					invokevirtual 52;		// init(Ljavacard/security/Key;B)V
					bspush 16;
					newarray 11;
					astore 18;
					bspush 16;
					newarray 11;
					astore 19;
				L10:	aload 17;
					aload 16;
					sconst_0;
					aload 16;
					arraylength;
					aload 18;
					sconst_0;
					invokevirtual 53;		// doFinal([BSS[BS)S
					pop;
					aload 17;
					getfield_a_this 25;		// reference be/msec/smartcard/IdentityCard.symKey
					sconst_2;
					invokevirtual 52;		// init(Ljavacard/security/Key;B)V
					aload 17;
					aload 9;
					sconst_0;
					aload 9;
					arraylength;
					aload 19;
					sconst_0;
					invokevirtual 53;		// doFinal([BSS[BS)S
					pop;
				L11:	goto L13;
				L12:	pop;
					sspush -30584;
					invokestatic 39;		// javacard/framework/ISOException.throwIt(S)V
				L13:	aload 15;
					arraylength;
					aload 18;
					arraylength;
					sadd;
					aload 19;
					arraylength;
					sadd;
					newarray 11;
					astore 20;
					aload 15;
					sconst_0;
					aload 20;
					sconst_0;
					aload 15;
					arraylength;
					invokestatic 54;		// javacard/framework/Util.arrayCopy([BS[BSS)S
					pop;
					aload 18;
					sconst_0;
					aload 20;
					aload 15;
					arraylength;
					aload 18;
					arraylength;
					invokestatic 54;		// javacard/framework/Util.arrayCopy([BS[BSS)S
					pop;
					aload 19;
					sconst_0;
					aload 20;
					aload 15;
					arraylength;
					aload 16;
					arraylength;
					sadd;
					aload 19;
					arraylength;
					invokestatic 54;		// javacard/framework/Util.arrayCopy([BS[BSS)S
					pop;
					aload_0;
					aload_1;
					aload 20;
					invokespecial 65;		// be/msec/smartcard/IdentityCard.sendChallengeToSP(Ljavacard/framework/APDU;[B)Z
					pop;
				L14:	goto L16;
				L15:	pop;
					sspush -30584;
					invokestatic 39;		// javacard/framework/ISOException.throwIt(S)V
				L16:	return;
			.exceptionTable {
				// start_block end_block handler_block catch_type_index
				L6 L7 L8 36;
				L10 L11 L12 36;
				L1 L14 L15 36;
			}
		}

		.method private sendChallengeToSP(Ljavacard/framework/APDU;[B)Z {
			.stack 4;
			.locals 4;

			.descriptor	Ljavacard/framework/APDU;	0.10;

				L0:	aload_2;
					arraylength;
					sstore_3;
				L1:	aload_1;
					invokevirtual 66;		// setOutgoing()S
					pop;
					aload_1;
					sload_3;
					invokevirtual 67;		// setOutgoingLength(S)V
					bspush 32;
					sstore 4;
					sconst_0;
					sstore 5;
					goto L5;
				L2:	sload_3;
					bspush 32;
					if_scmpge L4;
				L3:	sload_3;
					sstore 4;
				L4:	aload_1;
					aload_2;
					bspush 32;
					sload 5;
					smul;
					sload 4;
					invokevirtual 71;		// sendBytesLong([BSS)V
					sinc 3 -32;
					sload 5;
					sconst_1;
					sadd;
					s2b;
					sstore 5;
				L5:	sload_3;
					ifgt L2;
				L6:	goto L15;
				L7:	astore 4;
					aload 4;
					instanceof 0 68;		// T_CLASSORINTERFACE javacard/framework/APDUException
					ifeq L11;
				L8:	aload 4;
					checkcast 0 68;		// T_CLASSORINTERFACE javacard/framework/APDUException
					astore 5;
					aload 5;
					invokevirtual 69;		// getReason()S
					sstore 6;
					sload 6;
					sconst_3;
					if_scmpne L10;
				L9:	sspush -26224;
					invokestatic 39;		// javacard/framework/ISOException.throwIt(S)V
					goto L14;
				L10:	sspush -30585;
					invokestatic 39;		// javacard/framework/ISOException.throwIt(S)V
					goto L14;
				L11:	aload 4;
					instanceof 0 70;		// T_CLASSORINTERFACE java/lang/ArrayIndexOutOfBoundsException
					ifeq L13;
				L12:	sspush -32767;
					invokestatic 39;		// javacard/framework/ISOException.throwIt(S)V
					goto L14;
				L13:	sspush -30584;
					invokestatic 39;		// javacard/framework/ISOException.throwIt(S)V
				L14:	sconst_0;
					sreturn;
				L15:	sconst_1;
					sreturn;
			.exceptionTable {
				// start_block end_block handler_block catch_type_index
				L1 L6 L7 36;
			}
		}

		.method private updateTime(Ljavacard/framework/APDU;)V {
			.stack 7;
			.locals 5;

			.descriptor	Ljavacard/framework/APDU;	0.10;

				L0:	aload_0;
					aload_1;
					invokespecial 49;		// be/msec/smartcard/IdentityCard.receiveBigData(Ljavacard/framework/APDU;)[B
					astore_2;
					bspush 64;
					newarray 11;
					astore_3;
					aload_2;
					aload_2;
					arraylength;
					bspush 8;
					ssub;
					getfield_a_this 23;		// reference be/msec/smartcard/IdentityCard.date
					sconst_0;
					bspush 8;
					invokestatic 54;		// javacard/framework/Util.arrayCopy([BS[BSS)S
					pop;
					aload_2;
					sconst_0;
					aload_3;
					sconst_0;
					bspush 64;
					invokestatic 54;		// javacard/framework/Util.arrayCopy([BS[BSS)S
					pop;
				L1:	bspush 10;
					sconst_0;
					invokestatic 55;		// javacard/security/Signature.getInstance(BZ)Ljavacard/security/Signature;
					astore 4;
					sconst_4;
					sspush 512;
					sconst_0;
					invokestatic 64;		// javacard/security/KeyBuilder.buildKey(BSZ)Ljavacard/security/Key;
					checkcast 0 56;		// T_CLASSORINTERFACE javacard/security/RSAPublicKey
					astore 5;
					aload 5;
					getfield_a_this 4;		// reference be/msec/smartcard/IdentityCard.pubExp_G
					getfield_s_this 17;		// short be/msec/smartcard/IdentityCard.offset
					sconst_3;
					invokeinterface 4 56 6;		// javacard/security/RSAPublicKey
					aload 5;
					getfield_a_this 5;		// reference be/msec/smartcard/IdentityCard.pubMod_G
					getfield_s_this 17;		// short be/msec/smartcard/IdentityCard.offset
					getfield_a_this 5;		// reference be/msec/smartcard/IdentityCard.pubMod_G
					arraylength;
					invokeinterface 4 56 7;		// javacard/security/RSAPublicKey
					aload 4;
					aload 5;
					sconst_2;
					invokevirtual 57;		// init(Ljavacard/security/Key;B)V
					aload 4;
					getfield_a_this 23;		// reference be/msec/smartcard/IdentityCard.date
					sconst_0;
					getfield_a_this 23;		// reference be/msec/smartcard/IdentityCard.date
					arraylength;
					aload_3;
					sconst_0;
					aload_3;
					arraylength;
					invokevirtual 58;		// verify([BSS[BSS)Z
					sstore 6;
					aload_0;
					getfield_a_this 6;		// reference be/msec/smartcard/IdentityCard.lastValidationTime
					getfield_a_this 23;		// reference be/msec/smartcard/IdentityCard.date
					invokespecial 59;		// be/msec/smartcard/IdentityCard.isSmaller([B[B)Z
					ifeq L5;
				L2:	aload_0;
					getfield_a_this 23;		// reference be/msec/smartcard/IdentityCard.date
					putfield_a 6;		// reference be/msec/smartcard/IdentityCard.lastValidationTime
				L3:	goto L5;
				L4:	pop;
					sspush -30584;
					invokestatic 39;		// javacard/framework/ISOException.throwIt(S)V
				L5:	return;
			.exceptionTable {
				// start_block end_block handler_block catch_type_index
				L1 L3 L4 36;
			}
		}

		.method private isSmaller([B[B)Z {
			.stack 3;
			.locals 1;

				L0:	aload_1;
					arraylength;
					aload_2;
					arraylength;
					if_scmpeq L4;
				L1:	aload_1;
					arraylength;
					aload_2;
					arraylength;
					if_scmpge L3;
				L2:	sconst_1;
					sreturn;
				L3:	sconst_0;
					sreturn;
				L4:	sconst_0;
					sstore_3;
					goto L10;
				L5:	aload_1;
					sload_3;
					baload;
					aload_2;
					sload_3;
					baload;
					if_scmple L7;
				L6:	sconst_0;
					sreturn;
				L7:	aload_1;
					sload_3;
					baload;
					aload_2;
					sload_3;
					baload;
					if_scmpge L9;
				L8:	sconst_1;
					sreturn;
				L9:	sinc 3 1;
				L10:	sload_3;
					aload_1;
					arraylength;
					if_scmplt L5;
				L11:	sconst_1;
					sreturn;
		}

		.method private receiveBigData(Ljavacard/framework/APDU;)[B {
			.stack 5;
			.locals 4;

			.descriptor	Ljavacard/framework/APDU;	0.10;

				L0:	aload_1;
					invokevirtual 72;		// getIncomingLength()S
					newarray 11;
					astore_2;
				L1:	sconst_0;
					sstore_3;
					aload_1;
					invokevirtual 72;		// getIncomingLength()S
					sstore 4;
					aload_1;
					invokevirtual 73;		// setIncomingAndReceive()S
					sstore 5;
					goto L3;
				L2:	aload_1;
					invokevirtual 37;		// getBuffer()[B
					aload_1;
					invokevirtual 74;		// getOffsetCdata()S
					aload_2;
					sload_3;
					sload 5;
					invokestatic 54;		// javacard/framework/Util.arrayCopy([BS[BSS)S
					pop;
					sload 4;
					sload 5;
					ssub;
					sstore 4;
					sload_3;
					sload 5;
					sadd;
					sstore_3;
					aload_1;
					aload_1;
					invokevirtual 74;		// getOffsetCdata()S
					invokevirtual 75;		// receiveBytes(S)S
					sstore 5;
				L3:	sload 4;
					ifgt L2;
				L4:	goto L8;
				L5:	astore_3;
					aload_3;
					instanceof 0 70;		// T_CLASSORINTERFACE java/lang/ArrayIndexOutOfBoundsException
					ifeq L7;
				L6:	sspush -32767;
					invokestatic 39;		// javacard/framework/ISOException.throwIt(S)V
					goto L8;
				L7:	sspush -30584;
					invokestatic 39;		// javacard/framework/ISOException.throwIt(S)V
				L8:	aload_2;
					areturn;
			.exceptionTable {
				// start_block end_block handler_block catch_type_index
				L1 L4 L5 36;
			}
		}

		.method private validatePIN(Ljavacard/framework/APDU;)V {
			.stack 4;
			.locals 1;

			.descriptor	Ljavacard/framework/APDU;	0.10;

				L0:	aload_1;
					invokevirtual 37;		// getBuffer()[B
					astore_2;
					aload_2;
					sconst_4;
					baload;
					sconst_4;
					if_scmpne L3;
				L1:	aload_1;
					invokevirtual 73;		// setIncomingAndReceive()S
					pop;
					getfield_a_this 22;		// reference be/msec/smartcard/IdentityCard.pin
					aload_2;
					sconst_5;
					sconst_4;
					invokevirtual 76;		// check([BSB)Z
					ifne L4;
				L2:	sspush 25344;
					invokestatic 39;		// javacard/framework/ISOException.throwIt(S)V
					goto L4;
				L3:	sspush 26368;
					invokestatic 39;		// javacard/framework/ISOException.throwIt(S)V
				L4:	return;
		}

		.method private getSymKey()Ljavacard/security/AESKey; {
			.stack 4;
			.locals 2;

			.descriptor	Ljavacard/security/AESKey;	2.20;

				L0:	sconst_1;
					invokestatic 77;		// javacard/security/RandomData.getInstance(B)Ljavacard/security/RandomData;
					astore_1;
					aload_0;
					bspush 16;
					sconst_1;
					invokestatic 61;		// javacard/framework/JCSystem.makeTransientByteArray(SB)[B
					putfield_a 26;		// reference be/msec/smartcard/IdentityCard.rnd
					aload_1;
					getfield_a_this 26;		// reference be/msec/smartcard/IdentityCard.rnd
					sconst_0;
					getfield_a_this 26;		// reference be/msec/smartcard/IdentityCard.rnd
					arraylength;
					invokevirtual 78;		// generateData([BSS)V
					bspush 15;
					sspush 128;
					sconst_0;
					invokestatic 64;		// javacard/security/KeyBuilder.buildKey(BSZ)Ljavacard/security/Key;
					checkcast 0 79;		// T_CLASSORINTERFACE javacard/security/AESKey
					astore_2;
					aload_2;
					getfield_a_this 26;		// reference be/msec/smartcard/IdentityCard.rnd
					sconst_0;
					invokeinterface 3 79 4;		// javacard/security/AESKey
					aload_2;
					areturn;
		}

		.method private generateRandomBytes()[B {
			.stack 4;
			.locals 1;

				L0:	sconst_1;
					invokestatic 77;		// javacard/security/RandomData.getInstance(B)Ljavacard/security/RandomData;
					astore_1;
					aload_0;
					bspush 16;
					sconst_1;
					invokestatic 61;		// javacard/framework/JCSystem.makeTransientByteArray(SB)[B
					putfield_a 26;		// reference be/msec/smartcard/IdentityCard.rnd
					aload_1;
					getfield_a_this 26;		// reference be/msec/smartcard/IdentityCard.rnd
					sconst_0;
					getfield_a_this 26;		// reference be/msec/smartcard/IdentityCard.rnd
					arraylength;
					invokevirtual 78;		// generateData([BSS)V
					getfield_a_this 26;		// reference be/msec/smartcard/IdentityCard.rnd
					areturn;
		}

		.method private sign(Ljavacard/framework/APDU;)V {
			.stack 6;
			.locals 4;

			.descriptor	Ljavacard/framework/APDU;	0.10;

				L0:	getfield_a_this 22;		// reference be/msec/smartcard/IdentityCard.pin
					invokevirtual 80;		// isValidated()Z
					ifne L2;
				L1:	sspush 25345;
					invokestatic 39;		// javacard/framework/ISOException.throwIt(S)V
					goto L7;
				L2:	bspush 100;
					newarray 11;
					astore_2;
					aload_1;
					invokevirtual 72;		// getIncomingLength()S
					newarray 11;
					astore_3;
					aload_1;
					invokevirtual 37;		// getBuffer()[B
					aload_1;
					invokevirtual 74;		// getOffsetCdata()S
					aload_3;
					sconst_0;
					aload_1;
					invokevirtual 72;		// getIncomingLength()S
					invokestatic 54;		// javacard/framework/Util.arrayCopy([BS[BSS)S
					pop;
					bspush 10;
					sconst_0;
					invokestatic 55;		// javacard/security/Signature.getInstance(BZ)Ljavacard/security/Signature;
					astore 4;
					aload 4;
					getfield_a_this 20;		// reference be/msec/smartcard/IdentityCard.privKey
					sconst_1;
					invokevirtual 57;		// init(Ljavacard/security/Key;B)V
					aload 4;
					aload_3;
					sconst_0;
					aload_3;
					arraylength;
					aload_2;
					sconst_0;
					invokevirtual 81;		// sign([BSS[BS)S
					sstore 5;
					aload_1;
					invokevirtual 66;		// setOutgoing()S
					pop;
					aload_1;
					sload 5;
					invokevirtual 67;		// setOutgoingLength(S)V
					aload_1;
					aload_2;
					sconst_0;
					sload 5;
					invokevirtual 71;		// sendBytesLong([BSS)V
				L3:	goto L7;
				L4:	astore_2;
					aload_2;
					instanceof 0 70;		// T_CLASSORINTERFACE java/lang/ArrayIndexOutOfBoundsException
					ifeq L6;
				L5:	sspush -32767;
					invokestatic 39;		// javacard/framework/ISOException.throwIt(S)V
					goto L7;
				L6:	sspush -30584;
					invokestatic 39;		// javacard/framework/ISOException.throwIt(S)V
				L7:	return;
			.exceptionTable {
				// start_block end_block handler_block catch_type_index
				L0 L3 L4 36;
			}
		}

		.method private getSerial(Ljavacard/framework/APDU;)V {
			.stack 4;
			.locals 0;

			.descriptor	Ljavacard/framework/APDU;	0.10;

				L0:	getfield_a_this 22;		// reference be/msec/smartcard/IdentityCard.pin
					invokevirtual 80;		// isValidated()Z
					ifne L2;
				L1:	sspush 25345;
					invokestatic 39;		// javacard/framework/ISOException.throwIt(S)V
					goto L3;
				L2:	aload_1;
					invokevirtual 66;		// setOutgoing()S
					pop;
					aload_1;
					getfield_a_this 15;		// reference be/msec/smartcard/IdentityCard.serial
					arraylength;
					invokevirtual 67;		// setOutgoingLength(S)V
					aload_1;
					getfield_a_this 15;		// reference be/msec/smartcard/IdentityCard.serial
					sconst_0;
					getfield_a_this 15;		// reference be/msec/smartcard/IdentityCard.serial
					arraylength;
					invokevirtual 71;		// sendBytesLong([BSS)V
				L3:	return;
		}

		.method private getName(Ljavacard/framework/APDU;)V {
			.stack 4;
			.locals 0;

			.descriptor	Ljavacard/framework/APDU;	0.10;

				L0:	getfield_a_this 22;		// reference be/msec/smartcard/IdentityCard.pin
					invokevirtual 80;		// isValidated()Z
					ifne L2;
				L1:	sspush 25345;
					invokestatic 39;		// javacard/framework/ISOException.throwIt(S)V
					goto L3;
				L2:	aload_1;
					invokevirtual 66;		// setOutgoing()S
					pop;
					aload_1;
					getfield_a_this 16;		// reference be/msec/smartcard/IdentityCard.name
					arraylength;
					invokevirtual 67;		// setOutgoingLength(S)V
					aload_1;
					getfield_a_this 16;		// reference be/msec/smartcard/IdentityCard.name
					sconst_0;
					getfield_a_this 16;		// reference be/msec/smartcard/IdentityCard.name
					arraylength;
					invokevirtual 71;		// sendBytesLong([BSS)V
				L3:	return;
		}

		.method private sendCertificate(Ljavacard/framework/APDU;)V {
			.stack 4;
			.locals 4;

			.descriptor	Ljavacard/framework/APDU;	0.10;

				L0:	getfield_a_this 7;		// reference be/msec/smartcard/IdentityCard.certificate
					arraylength;
					sstore_2;
				L1:	aload_1;
					invokevirtual 66;		// setOutgoing()S
					pop;
					aload_1;
					sload_2;
					invokevirtual 67;		// setOutgoingLength(S)V
					bspush 32;
					sstore_3;
					sconst_0;
					sstore 4;
					goto L5;
				L2:	sload_2;
					bspush 32;
					if_scmpge L4;
				L3:	sload_2;
					sstore_3;
				L4:	aload_1;
					getfield_a_this 7;		// reference be/msec/smartcard/IdentityCard.certificate
					bspush 32;
					sload 4;
					smul;
					sload_3;
					invokevirtual 71;		// sendBytesLong([BSS)V
					sinc 2 -32;
					sload 4;
					sconst_1;
					sadd;
					s2b;
					sstore 4;
				L5:	sload_2;
					ifgt L2;
				L6:	goto L14;
				L7:	astore_3;
					aload_3;
					instanceof 0 68;		// T_CLASSORINTERFACE javacard/framework/APDUException
					ifeq L11;
				L8:	aload_3;
					checkcast 0 68;		// T_CLASSORINTERFACE javacard/framework/APDUException
					astore 4;
					aload 4;
					invokevirtual 69;		// getReason()S
					sstore 5;
					sload 5;
					sconst_3;
					if_scmpne L10;
				L9:	sspush -26224;
					invokestatic 39;		// javacard/framework/ISOException.throwIt(S)V
					goto L14;
				L10:	sspush -30585;
					invokestatic 39;		// javacard/framework/ISOException.throwIt(S)V
					goto L14;
				L11:	aload_3;
					instanceof 0 70;		// T_CLASSORINTERFACE java/lang/ArrayIndexOutOfBoundsException
					ifeq L13;
				L12:	sspush -32767;
					invokestatic 39;		// javacard/framework/ISOException.throwIt(S)V
					goto L14;
				L13:	sspush -30584;
					invokestatic 39;		// javacard/framework/ISOException.throwIt(S)V
				L14:	return;
			.exceptionTable {
				// start_block end_block handler_block catch_type_index
				L1 L6 L7 36;
			}
		}

	}

}
